{"items":[{"body":[{"value":{"color":"blue","name":"image","label":"Image or Drawing"},"type":"CategoryLabel"}],"created":"2019-08-30T18:53:43.946Z","target":[{"type":"SpecificResource","source":"https://kjc-sv002.kjc.uni-heidelberg.de:8080/fcgi-bin/iipsrv.fcgi?IIIF=imageStorage/ecpo_new/jingbao/1939/04/jb_3796_1939-04-22_0005%252B0008.tif/full/full/0/default.jpg","id":"s-15671912239394","selector":{"value":"<g transform=\"matrix(1 0 0 1 1911.74 498.64)\" id=\"s-15671912239394\">\n<polygon points=\"-178.55,-52.78 178.54,-51.14 178.54,51.4 -176.94,52.78 \"/>\n</g>","type":"SvgSelector"}}],"type":"Annotation","id":"s-1567191223946"},{"body":[{"value":{"color":"orange","name":"article","label":"Article"},"type":"CategoryLabel"}],"created":"2019-08-30T18:54:12.991Z","target":[{"type":"SpecificResource","source":"https://kjc-sv002.kjc.uni-heidelberg.de:8080/fcgi-bin/iipsrv.fcgi?IIIF=imageStorage/ecpo_new/jingbao/1939/04/jb_3796_1939-04-22_0005%252B0008.tif/full/full/0/default.jpg","id":"s-15671912529876","selector":{"value":"<g transform=\"matrix(1 0 0 1 1898.19 1068.71)\" id=\"s-15671912529876\">\n<polygon points=\"-147.93,-23.19 147.92,-21.59 146.34,23.19 -147.93,21.59 \"/>\n</g>","type":"SvgSelector"}}],"type":"Annotation","id":"s-1567191252991"},{"body":[{"value":{"color":"orange","name":"article","label":"Article"},"type":"CategoryLabel"}],"created":"2019-08-30T18:55:03.943Z","target":[{"type":"SpecificResource","source":"https://kjc-sv002.kjc.uni-heidelberg.de:8080/fcgi-bin/iipsrv.fcgi?IIIF=imageStorage/ecpo_new/jingbao/1939/04/jb_3796_1939-04-22_0005%252B0008.tif/full/full/0/default.jpg","id":"s-15671913036509","selector":{"value":"<g transform=\"matrix(1 0 0 1 1857.34 1203.96)\" id=\"s-15671913036509\">\n<polygon points=\"-181.06,-104.75 185.61,-102.24 184.7,104.75 -185.61,102.93 \"/>\n</g>","type":"SvgSelector"}}],"type":"Annotation","id":"s-1567191303943"},{"body":[{"value":{"color":"orange","name":"article","label":"Article"},"type":"CategoryLabel"}],"created":"2019-08-30T18:55:20.669Z","target":[{"type":"SpecificResource","source":"https://kjc-sv002.kjc.uni-heidelberg.de:8080/fcgi-bin/iipsrv.fcgi?IIIF=imageStorage/ecpo_new/jingbao/1939/04/jb_3796_1939-04-22_0005%252B0008.tif/full/full/0/default.jpg","id":"s-15671913206651","selector":{"value":"<g transform=\"matrix(1 0 0 1 1853.27 1424.56)\" id=\"s-15671913206651\">\n<polygon points=\"-185.39,-103.95 187.21,-100.75 184.01,103.95 -187.21,98.93 \"/>\n</g>","type":"SvgSelector"}}],"type":"Annotation","id":"s-1567191320669"},{"body":[{"value":{"color":"orange","name":"article","label":"Article"},"type":"CategoryLabel"}],"created":"2019-08-30T18:55:54.154Z","target":[{"type":"SpecificResource","source":"https://kjc-sv002.kjc.uni-heidelberg.de:8080/fcgi-bin/iipsrv.fcgi?IIIF=imageStorage/ecpo_new/jingbao/1939/04/jb_3796_1939-04-22_0005%252B0008.tif/full/full/0/default.jpg","id":"s-15671913541452","selector":{"value":"<g transform=\"matrix(1 0 0 1 1883.42 1642.62)\" id=\"s-15671913541452\">\n<polygon points=\"-216.92,-107.94 219.66,-99.47 216.24,107.94 -219.66,105.43 \"/>\n</g>","type":"SvgSelector"}}],"type":"Annotation","id":"s-1567191354154"},{"body":[{"value":{"color":"orange","name":"article","label":"Article"},"type":"CategoryLabel"}],"created":"2019-08-30T19:58:33.786Z","target":[{"type":"SpecificResource","source":"https://kjc-sv002.kjc.uni-heidelberg.de:8080/fcgi-bin/iipsrv.fcgi?IIIF=imageStorage/ecpo_new/jingbao/1939/04/jb_3796_1939-04-22_0005%252B0008.tif/full/full/0/default.jpg","id":"s-15671951137816","selector":{"value":"<g transform=\"matrix(1 0 0 1 1320.18 1419.45)\" id=\"s-15671951137816\">\n<polygon points=\"-334.5,-104.6 334.5,-97.94 331.83,104.61 -333.16,100.62 \"/>\n</g>","type":"SvgSelector"}}],"type":"Annotation","id":"s-1567195113786"},{"body":[{"value":{"color":"orange","name":"article","label":"Article"},"type":"CategoryLabel"}],"created":"2019-08-31T17:25:36.521Z","target":[{"type":"SpecificResource","source":"https://kjc-sv002.kjc.uni-heidelberg.de:8080/fcgi-bin/iipsrv.fcgi?IIIF=imageStorage/ecpo_new/jingbao/1939/04/jb_3796_1939-04-22_0005%252B0008.tif/full/full/0/default.jpg","id":"s-15672723365060","selector":{"value":"<g transform=\"matrix(1 0 0 1 1267.29 870.37)\" id=\"s-15672723365060\">\n<polygon points=\"-326.83,-436.4 341.52,-433.28 324.61,436.41 -341.52,432.31 \"/>\n</g>","type":"SvgSelector"}}],"type":"Annotation","id":"s-1567272336521"},{"body":[{"color":"#a1887f","width":442.18000000000006,"left":1663.26,"height":652.3499999999999,"top":1098.71,"type":"GroupAnnotation","id":"s-16605769820939"},{"value":{"color":"","name":"article","label":""},"type":"CategoryLabel"}],"created":"2022-08-15T15:23:02.093Z","target":[{"type":"SpecificResource","source":"https://kjc-sv002.kjc.uni-heidelberg.de:8080/fcgi-bin/iipsrv.fcgi?IIIF=imageStorage/ecpo_new/jingbao/1939/04/jb_3796_1939-04-22_0005%252B0008.tif/full/full/0/default.jpg","id":"s-16605768181408","selector":{"value":"<g transform=\"matrix(1 0 0 1 2077.16 1250.13)\" id=\"s-16605768181408\">\n<polygon points=\"-27.78,-117.69 27.78,-117.69 27.78,117.69 -27.78,117.69 \"/>\n</g>","type":"SvgSelector"}},{"type":"SpecificResource","source":"https://kjc-sv002.kjc.uni-heidelberg.de:8080/fcgi-bin/iipsrv.fcgi?IIIF=imageStorage/ecpo_new/jingbao/1939/04/jb_3796_1939-04-22_0005%252B0008.tif/full/full/0/default.jpg","id":"s-16605768207001","selector":{"value":"<g transform=\"matrix(1 0 0 1 2075.17 1441.87)\" id=\"s-16605768207001\">\n<polygon points=\"-20.51,-58.18 20.51,-58.18 20.51,58.18 -20.51,58.18 \"/>\n</g>","type":"SvgSelector"}},{"type":"SpecificResource","source":"https://kjc-sv002.kjc.uni-heidelberg.de:8080/fcgi-bin/iipsrv.fcgi?IIIF=imageStorage/ecpo_new/jingbao/1939/04/jb_3796_1939-04-22_0005%252B0008.tif/full/full/0/default.jpg","id":"s-15671913206651","selector":{"value":"<g transform=\"matrix(1 0 0 1 1853.27 1424.56)\" id=\"s-15671913206651\">\n<polygon points=\"-185.39,-103.95 187.21,-100.75 184.01,103.95 -187.21,98.93 \"/>\n</g>","type":"SvgSelector"}},{"type":"SpecificResource","source":"https://kjc-sv002.kjc.uni-heidelberg.de:8080/fcgi-bin/iipsrv.fcgi?IIIF=imageStorage/ecpo_new/jingbao/1939/04/jb_3796_1939-04-22_0005%252B0008.tif/full/full/0/default.jpg","id":"s-15671913036509","selector":{"value":"<g transform=\"matrix(1 0 0 1 1857.34 1203.96)\" id=\"s-15671913036509\">\n<polygon points=\"-181.06,-104.75 185.61,-102.24 184.7,104.75 -185.61,102.93 \"/>\n</g>","type":"SvgSelector"}},{"type":"SpecificResource","source":"https://kjc-sv002.kjc.uni-heidelberg.de:8080/fcgi-bin/iipsrv.fcgi?IIIF=imageStorage/ecpo_new/jingbao/1939/04/jb_3796_1939-04-22_0005%252B0008.tif/full/full/0/default.jpg","id":"s-15671913541452","selector":{"value":"<g transform=\"matrix(1 0 0 1 1883.42 1642.62)\" id=\"s-15671913541452\">\n<polygon points=\"-216.92,-107.94 219.66,-99.47 216.24,107.94 -219.66,105.43 \"/>\n</g>","type":"SvgSelector"}}],"type":"Annotation","id":"s-16605769820939"},{"body":[{"value":{"color":"orange","name":"article","label":"Article"},"type":"CategoryLabel"}],"created":"2019-08-31T17:26:50.369Z","target":[{"type":"SpecificResource","source":"https://kjc-sv002.kjc.uni-heidelberg.de:8080/fcgi-bin/iipsrv.fcgi?IIIF=imageStorage/ecpo_new/jingbao/1939/04/jb_3796_1939-04-22_0005%252B0008.tif/full/full/0/default.jpg","id":"s-15672724103643","selector":{"value":"<g transform=\"matrix(1 0 0 1 880.96 961.45)\" id=\"s-15672724103643\">\n<polygon points=\"-33.13,-83.78 38.59,-83.78 34.96,83.78 -38.59,82.87 \"/>\n</g>","type":"SvgSelector"}}],"type":"Annotation","id":"s-1567272410369"},{"body":[{"value":{"color":"orange","name":"article","label":"Article"},"type":"CategoryLabel"}],"created":"2019-08-31T17:26:58.321Z","target":[{"type":"SpecificResource","source":"https://kjc-sv002.kjc.uni-heidelberg.de:8080/fcgi-bin/iipsrv.fcgi?IIIF=imageStorage/ecpo_new/jingbao/1939/04/jb_3796_1939-04-22_0005%252B0008.tif/full/full/0/default.jpg","id":"s-15672724183164","selector":{"value":"<g transform=\"matrix(1 0 0 1 573.98 535.02)\" id=\"s-15672724183164\">\n<polygon points=\"-165.09,-106.9 169.94,-100.86 164.81,106.89 -169.94,99.95 \"/>\n</g>","type":"SvgSelector"}}],"type":"Annotation","id":"s-1567272418321"},{"body":[{"value":{"color":"orange","name":"article","label":"Article"},"type":"CategoryLabel"}],"created":"2019-08-31T17:27:25.608Z","target":[{"type":"SpecificResource","source":"https://kjc-sv002.kjc.uni-heidelberg.de:8080/fcgi-bin/iipsrv.fcgi?IIIF=imageStorage/ecpo_new/jingbao/1939/04/jb_3796_1939-04-22_0005%252B0008.tif/full/full/0/default.jpg","id":"s-15672724456045","selector":{"value":"<g transform=\"matrix(1 0 0 1 568.85 759.09)\" id=\"s-15672724456045\">\n<polygon points=\"-162.98,-105.38 169.52,-101.45 165.6,105.38 -169.52,98.83 \"/>\n</g>","type":"SvgSelector"}}],"type":"Annotation","id":"s-1567272445608"},{"body":[{"value":{"color":"orange","name":"article","label":"Article"},"type":"CategoryLabel"}],"created":"2019-08-31T17:27:49.943Z","target":[{"type":"SpecificResource","source":"https://kjc-sv002.kjc.uni-heidelberg.de:8080/fcgi-bin/iipsrv.fcgi?IIIF=imageStorage/ecpo_new/jingbao/1939/04/jb_3796_1939-04-22_0005%252B0008.tif/full/full/0/default.jpg","id":"s-15672724699383","selector":{"value":"<g transform=\"matrix(1 0 0 1 562.46 977.04)\" id=\"s-15672724699383\">\n<polygon points=\"-164.95,-106.04 168.87,-98.18 164.94,106.04 -168.87,96.87 \"/>\n</g>","type":"SvgSelector"}}],"type":"Annotation","id":"s-1567272469943"},{"body":[{"value":{"color":"orange","name":"article","label":"Article"},"type":"CategoryLabel"}],"created":"2019-08-31T17:28:14.993Z","target":[{"type":"SpecificResource","source":"https://kjc-sv002.kjc.uni-heidelberg.de:8080/fcgi-bin/iipsrv.fcgi?IIIF=imageStorage/ecpo_new/jingbao/1939/04/jb_3796_1939-04-22_0005%252B0008.tif/full/full/0/default.jpg","id":"s-15672724949871","selector":{"value":"<g transform=\"matrix(1 0 0 1 653.23 1198.48)\" id=\"s-15672724949871\">\n<polygon points=\"-258.57,-106.95 262.88,-99.09 257.63,106.95 -262.88,98.3 \"/>\n</g>","type":"SvgSelector"}}],"type":"Annotation","id":"s-1567272494993"},{"body":[{"value":{"color":"orange","name":"article","label":"Article"},"type":"CategoryLabel"}],"created":"2019-08-31T17:36:45.073Z","target":[{"type":"SpecificResource","source":"https://kjc-sv002.kjc.uni-heidelberg.de:8080/fcgi-bin/iipsrv.fcgi?IIIF=imageStorage/ecpo_new/jingbao/1939/04/jb_3796_1939-04-22_0005%252B0008.tif/full/full/0/default.jpg","id":"s-15672730050628","selector":{"value":"<g transform=\"matrix(1 0 0 1 681.59 1416.67)\" id=\"s-15672730050628\">\n<polygon points=\"-294.54,-105.81 302.18,-99.28 301.09,105.81 -302.18,102.55 \"/>\n</g>","type":"SvgSelector"}}],"type":"Annotation","id":"s-1567273005072"},{"body":[{"value":{"color":"orange","name":"article","label":"Article"},"type":"CategoryLabel"}],"created":"2019-08-31T19:14:46.103Z","target":[{"type":"SpecificResource","source":"https://kjc-sv002.kjc.uni-heidelberg.de:8080/fcgi-bin/iipsrv.fcgi?IIIF=imageStorage/ecpo_new/jingbao/1939/04/jb_3796_1939-04-22_0005%252B0008.tif/full/full/0/default.jpg","id":"s-156727888609210","selector":{"value":"<g transform=\"matrix(1 0 0 1 705.44 1758)\" id=\"s-156727888609210\">\n<polygon points=\"-318.22,-192.7 322.05,-187.77 317.99,192.7 -322.05,187.08 \"/>\n</g>","type":"SvgSelector"}}],"type":"Annotation","id":"s-1567278886103"},{"body":[{"value":{"color":"blue","name":"image","label":"Image or Drawing"},"type":"CategoryLabel"}],"created":"2019-08-31T19:15:37.414Z","target":[{"type":"SpecificResource","source":"https://kjc-sv002.kjc.uni-heidelberg.de:8080/fcgi-bin/iipsrv.fcgi?IIIF=imageStorage/ecpo_new/jingbao/1939/04/jb_3796_1939-04-22_0005%252B0008.tif/full/full/0/default.jpg","id":"s-15672789374050","selector":{"value":"<g transform=\"matrix(1 0 0 1 671.37 2592.09)\" id=\"s-15672789374050\">\n<polygon points=\"-296.67,-476.7 313.71,-473.93 296.53,476.7 -313.71,475.74 \"/>\n</g>","type":"SvgSelector"}}],"type":"Annotation","id":"s-1567278937414"},{"body":[{"value":{"color":"orange","name":"article","label":"Article"},"type":"CategoryLabel"}],"created":"2019-08-31T19:16:30.436Z","target":[{"type":"SpecificResource","source":"https://kjc-sv002.kjc.uni-heidelberg.de:8080/fcgi-bin/iipsrv.fcgi?IIIF=imageStorage/ecpo_new/jingbao/1939/04/jb_3796_1939-04-22_0005%252B0008.tif/full/full/0/default.jpg","id":"s-15672789904283","selector":{"value":"<g transform=\"matrix(1 0 0 1 1344.7 1641.66)\" id=\"s-15672789904283\">\n<polygon points=\"-300.09,-106.43 304.02,-100.41 300.07,106.43 -304.02,97.27 \"/>\n</g>","type":"SvgSelector"}}],"type":"Annotation","id":"s-1567278990436"},{"body":[{"value":{"color":"orange","name":"article","label":"Article"},"type":"CategoryLabel"}],"created":"2019-08-31T19:17:02.275Z","target":[{"type":"SpecificResource","source":"https://kjc-sv002.kjc.uni-heidelberg.de:8080/fcgi-bin/iipsrv.fcgi?IIIF=imageStorage/ecpo_new/jingbao/1939/04/jb_3796_1939-04-22_0005%252B0008.tif/full/full/0/default.jpg","id":"s-15672790222699","selector":{"value":"<g transform=\"matrix(1 0 0 1 1229.04 1861.13)\" id=\"s-15672790222699\">\n<polygon points=\"-186.43,-104.38 188.25,-102.57 186.03,101.25 -188.25,104.38 \"/>\n</g>","type":"SvgSelector"}}],"type":"Annotation","id":"s-1567279022275"},{"body":[{"value":{"color":"orange","name":"article","label":"Article"},"type":"CategoryLabel"}],"created":"2019-08-31T19:17:17.323Z","target":[{"type":"SpecificResource","source":"https://kjc-sv002.kjc.uni-heidelberg.de:8080/fcgi-bin/iipsrv.fcgi?IIIF=imageStorage/ecpo_new/jingbao/1939/04/jb_3796_1939-04-22_0005%252B0008.tif/full/full/0/default.jpg","id":"s-15672790373178","selector":{"value":"<g transform=\"matrix(1 0 0 1 1723.95 1865.26)\" id=\"s-15672790373178\">\n<polygon points=\"-291.44,-107.61 293.44,-100.16 290.83,107.61 -293.44,97.92 \"/>\n</g>","type":"SvgSelector"}}],"type":"Annotation","id":"s-1567279037323"},{"body":[{"value":{"color":"orange","name":"article","label":"Article"},"type":"CategoryLabel"}],"created":"2019-08-31T19:18:07.911Z","target":[{"type":"SpecificResource","source":"https://kjc-sv002.kjc.uni-heidelberg.de:8080/fcgi-bin/iipsrv.fcgi?IIIF=imageStorage/ecpo_new/jingbao/1939/04/jb_3796_1939-04-22_0005%252B0008.tif/full/full/0/default.jpg","id":"s-15672790879088","selector":{"value":"<g transform=\"matrix(1 0 0 1 2052.2 2288)\" id=\"s-15672790879088\">\n<polygon points=\"-44.51,-93.59 44.51,-92.28 40.58,93.59 -44.51,92.3 \"/>\n</g>","type":"SvgSelector"}}],"type":"Annotation","id":"s-1567279087911"},{"body":[{"value":{"color":"orange","name":"article","label":"Article"},"type":"CategoryLabel"}],"created":"2019-08-31T19:18:30.652Z","target":[{"type":"SpecificResource","source":"https://kjc-sv002.kjc.uni-heidelberg.de:8080/fcgi-bin/iipsrv.fcgi?IIIF=imageStorage/ecpo_new/jingbao/1939/04/jb_3796_1939-04-22_0005%252B0008.tif/full/full/0/default.jpg","id":"s-15672791106472","selector":{"value":"<g transform=\"matrix(1 0 0 1 1719.32 2086.54)\" id=\"s-15672791106472\">\n<polygon points=\"-288.91,-109.41 292.84,-100.14 288.4,109.42 -292.84,102.76 \"/>\n</g>","type":"SvgSelector"}}],"type":"Annotation","id":"s-1567279110652"},{"body":[{"value":{"color":"orange","name":"article","label":"Article"},"type":"CategoryLabel"}],"created":"2019-08-31T19:18:52.015Z","target":[{"type":"SpecificResource","source":"https://kjc-sv002.kjc.uni-heidelberg.de:8080/fcgi-bin/iipsrv.fcgi?IIIF=imageStorage/ecpo_new/jingbao/1939/04/jb_3796_1939-04-22_0005%252B0008.tif/full/full/0/default.jpg","id":"s-15672791320115","selector":{"value":"<g transform=\"matrix(1 0 0 1 1210.86 2080.4)\" id=\"s-15672791320115\">\n<polygon points=\"-202.41,-103.22 203.41,-101.4 200.81,103.22 -203.42,101.41 \"/>\n</g>","type":"SvgSelector"}}],"type":"Annotation","id":"s-1567279132015"},{"body":[{"value":{"color":"orange","name":"article","label":"Article"},"type":"CategoryLabel"}],"created":"2019-08-31T19:19:21.920Z","target":[{"type":"SpecificResource","source":"https://kjc-sv002.kjc.uni-heidelberg.de:8080/fcgi-bin/iipsrv.fcgi?IIIF=imageStorage/ecpo_new/jingbao/1939/04/jb_3796_1939-04-22_0005%252B0008.tif/full/full/0/default.jpg","id":"s-15672791619163","selector":{"value":"<g transform=\"matrix(1 0 0 1 1203.98 2300.53)\" id=\"s-15672791619163\">\n<polygon points=\"-198.12,-104.72 205.08,-100.8 202.86,104.72 -205.07,96.88 \"/>\n</g>","type":"SvgSelector"}}],"type":"Annotation","id":"s-1567279161920"},{"body":[{"value":{"color":"orange","name":"article","label":"Article"},"type":"CategoryLabel"}],"created":"2019-08-31T19:19:42.272Z","target":[{"type":"SpecificResource","source":"https://kjc-sv002.kjc.uni-heidelberg.de:8080/fcgi-bin/iipsrv.fcgi?IIIF=imageStorage/ecpo_new/jingbao/1939/04/jb_3796_1939-04-22_0005%252B0008.tif/full/full/0/default.jpg","id":"s-15672791822688","selector":{"value":"<g transform=\"matrix(1 0 0 1 1199.85 2523.26)\" id=\"s-15672791822688\">\n<polygon points=\"-200.95,-104.94 206.18,-102.31 203.96,104.02 -206.18,104.94 \"/>\n</g>","type":"SvgSelector"}}],"type":"Annotation","id":"s-1567279182272"},{"body":[{"value":{"color":"orange","name":"article","label":"Article"},"type":"CategoryLabel"}],"created":"2019-08-31T19:20:03.272Z","target":[{"type":"SpecificResource","source":"https://kjc-sv002.kjc.uni-heidelberg.de:8080/fcgi-bin/iipsrv.fcgi?IIIF=imageStorage/ecpo_new/jingbao/1939/04/jb_3796_1939-04-22_0005%252B0008.tif/full/full/0/default.jpg","id":"s-15672792032698","selector":{"value":"<g transform=\"matrix(1 0 0 1 1194.74 2748.9)\" id=\"s-15672792032698\">\n<polygon points=\"-200.28,-105.39 206.84,-105.39 204.22,105.39 -206.84,104.08 \"/>\n</g>","type":"SvgSelector"}}],"type":"Annotation","id":"s-1567279203272"},{"body":[{"value":{"color":"orange","name":"article","label":"Article"},"type":"CategoryLabel"}],"created":"2019-08-31T19:20:21.303Z","target":[{"type":"SpecificResource","source":"https://kjc-sv002.kjc.uni-heidelberg.de:8080/fcgi-bin/iipsrv.fcgi?IIIF=imageStorage/ecpo_new/jingbao/1939/04/jb_3796_1939-04-22_0005%252B0008.tif/full/full/0/default.jpg","id":"s-156727922130010","selector":{"value":"<g transform=\"matrix(1 0 0 1 1190.42 2968.97)\" id=\"s-156727922130010\">\n<polygon points=\"-204.22,-103.42 204.22,-102.1 202.91,103.42 -204.22,102.12 \"/>\n</g>","type":"SvgSelector"}}],"type":"Annotation","id":"s-1567279221303"},{"body":[{"value":{"color":"orange","name":"article","label":"Article"},"type":"CategoryLabel"}],"created":"2019-08-31T19:20:41.690Z","target":[{"type":"SpecificResource","source":"https://kjc-sv002.kjc.uni-heidelberg.de:8080/fcgi-bin/iipsrv.fcgi?IIIF=imageStorage/ecpo_new/jingbao/1939/04/jb_3796_1939-04-22_0005%252B0008.tif/full/full/0/default.jpg","id":"s-15672792416855","selector":{"value":"<g transform=\"matrix(1 0 0 1 1713.22 2312.58)\" id=\"s-15672792416855\">\n<polygon points=\"-285.46,-106.7 288.46,-98.85 285.84,106.7 -288.46,97.02 \"/>\n</g>","type":"SvgSelector"}}],"type":"Annotation","id":"s-1567279241690"},{"body":[{"value":{"color":"orange","name":"article","label":"Article"},"type":"CategoryLabel"}],"created":"2019-08-31T19:21:03.519Z","target":[{"type":"SpecificResource","source":"https://kjc-sv002.kjc.uni-heidelberg.de:8080/fcgi-bin/iipsrv.fcgi?IIIF=imageStorage/ecpo_new/jingbao/1939/04/jb_3796_1939-04-22_0005%252B0008.tif/full/full/0/default.jpg","id":"s-15672792635157","selector":{"value":"<g transform=\"matrix(1 0 0 1 1759.43 2530.19)\" id=\"s-15672792635157\">\n<polygon points=\"-332.87,-107.1 333.88,-96.11 329.84,107.1 -333.88,101.97 \"/>\n</g>","type":"SvgSelector"}}],"type":"Annotation","id":"s-1567279263519"},{"body":[{"value":{"color":"orange","name":"article","label":"Article"},"type":"CategoryLabel"}],"created":"2019-08-31T19:21:28.023Z","target":[{"type":"SpecificResource","source":"https://kjc-sv002.kjc.uni-heidelberg.de:8080/fcgi-bin/iipsrv.fcgi?IIIF=imageStorage/ecpo_new/jingbao/1939/04/jb_3796_1939-04-22_0005%252B0008.tif/full/full/0/default.jpg","id":"s-15672792880194","selector":{"value":"<g transform=\"matrix(1 0 0 1 1752.03 2753)\" id=\"s-15672792880194\">\n<polygon points=\"-333.81,-104.72 336.44,-100.8 331.19,104.73 -336.44,103.42 \"/>\n</g>","type":"SvgSelector"}}],"type":"Annotation","id":"s-1567279288023"},{"body":[{"value":{"color":"orange","name":"article","label":"Article"},"type":"CategoryLabel"}],"created":"2019-08-31T19:21:49.136Z","target":[{"type":"SpecificResource","source":"https://kjc-sv002.kjc.uni-heidelberg.de:8080/fcgi-bin/iipsrv.fcgi?IIIF=imageStorage/ecpo_new/jingbao/1939/04/jb_3796_1939-04-22_0005%252B0008.tif/full/full/0/default.jpg","id":"s-15672793091310","selector":{"value":"<g transform=\"matrix(1 0 0 1 1747.69 2974.85)\" id=\"s-15672793091310\">\n<polygon points=\"-331.2,-104.08 335.13,-101.44 332.51,104.08 -335.13,98.84 \"/>\n</g>","type":"SvgSelector"}}],"type":"Annotation","id":"s-1567279309136"},{"body":[{"value":{"color":"purple","name":"additional","label":"Additional Information"},"type":"CategoryLabel"}],"created":"2019-08-31T19:22:30.912Z","target":[{"type":"SpecificResource","source":"https://kjc-sv002.kjc.uni-heidelberg.de:8080/fcgi-bin/iipsrv.fcgi?IIIF=imageStorage/ecpo_new/jingbao/1939/04/jb_3796_1939-04-22_0005%252B0008.tif/full/full/0/default.jpg","id":"s-15672793509082","selector":{"value":"<g transform=\"matrix(1 0 0 1 571.11 342.45)\" id=\"s-15672793509082\">\n<polygon points=\"-62.19,-23.49 63.09,-23.49 61.27,22.58 -63.09,23.49 \"/>\n</g>","type":"SvgSelector"}}],"type":"Annotation","id":"s-1567279350912"},{"body":[{"value":{"color":"purple","name":"additional","label":"Additional Information"},"type":"CategoryLabel"}],"created":"2019-08-31T19:22:34.470Z","target":[{"type":"SpecificResource","source":"https://kjc-sv002.kjc.uni-heidelberg.de:8080/fcgi-bin/iipsrv.fcgi?IIIF=imageStorage/ecpo_new/jingbao/1939/04/jb_3796_1939-04-22_0005%252B0008.tif/full/full/0/default.jpg","id":"s-15672793544662","selector":{"value":"<g transform=\"matrix(1 0 0 1 880.8 342.65)\" id=\"s-15672793544662\">\n<polygon points=\"-63.72,-21.43 63.71,-20.53 61.89,21.43 -62.81,20.52 \"/>\n</g>","type":"SvgSelector"}}],"type":"Annotation","id":"s-1567279354470"},{"body":[{"value":{"color":"purple","name":"additional","label":"Additional Information"},"type":"CategoryLabel"}],"created":"2019-08-31T19:22:37.990Z","target":[{"type":"SpecificResource","source":"https://kjc-sv002.kjc.uni-heidelberg.de:8080/fcgi-bin/iipsrv.fcgi?IIIF=imageStorage/ecpo_new/jingbao/1939/04/jb_3796_1939-04-22_0005%252B0008.tif/full/full/0/default.jpg","id":"s-15672793579877","selector":{"value":"<g transform=\"matrix(1 0 0 1 1245.53 350.86)\" id=\"s-15672793579877\">\n<polygon points=\"-116.5,-54.29 116.5,-54.29 116.5,54.29 -116.5,54.29 \"/>\n</g>","type":"SvgSelector"}}],"type":"Annotation","id":"s-1567279357990"},{"body":[{"value":{"color":"purple","name":"additional","label":"Additional Information"},"type":"CategoryLabel"}],"created":"2019-08-31T19:22:42.126Z","target":[{"type":"SpecificResource","source":"https://kjc-sv002.kjc.uni-heidelberg.de:8080/fcgi-bin/iipsrv.fcgi?IIIF=imageStorage/ecpo_new/jingbao/1939/04/jb_3796_1939-04-22_0005%252B0008.tif/full/full/0/default.jpg","id":"s-15672793621237","selector":{"value":"<g transform=\"matrix(1 0 0 1 1769.21 345.21)\" id=\"s-15672793621237\">\n<polygon points=\"-262.4,-32.8 262.4,-32.8 262.4,32.8 -262.4,32.8 \"/>\n</g>","type":"SvgSelector"}}],"type":"Annotation","id":"s-1567279362126"},{"body":[{"value":{"color":"purple","name":"additional","label":"Additional Information"},"type":"CategoryLabel"}],"created":"2019-08-31T19:22:55.679Z","target":[{"type":"SpecificResource","source":"https://kjc-sv002.kjc.uni-heidelberg.de:8080/fcgi-bin/iipsrv.fcgi?IIIF=imageStorage/ecpo_new/jingbao/1939/04/jb_3796_1939-04-22_0005%252B0008.tif/full/full/0/default.jpg","id":"s-15672793756765","selector":{"value":"<g transform=\"matrix(1 0 0 1 3955.48 363.26)\" id=\"s-15672793756765\">\n<polygon points=\"-260.14,-33.92 260.14,-29.38 259.23,33.92 -259.23,30.28 \"/>\n</g>","type":"SvgSelector"}}],"type":"Annotation","id":"s-1567279375679"},{"body":[{"value":{"color":"purple","name":"additional","label":"Additional Information"},"type":"CategoryLabel"}],"created":"2019-08-31T19:22:58.973Z","target":[{"type":"SpecificResource","source":"https://kjc-sv002.kjc.uni-heidelberg.de:8080/fcgi-bin/iipsrv.fcgi?IIIF=imageStorage/ecpo_new/jingbao/1939/04/jb_3796_1939-04-22_0005%252B0008.tif/full/full/0/default.jpg","id":"s-15672793789700","selector":{"value":"<g transform=\"matrix(1 0 0 1 3439.27 359.18)\" id=\"s-15672793789700\">\n<polygon points=\"-119.89,-58.81 119.89,-58.81 119.89,58.81 -119.89,58.81 \"/>\n</g>","type":"SvgSelector"}}],"type":"Annotation","id":"s-1567279378973"},{"body":[{"value":{"color":"purple","name":"additional","label":"Additional Information"},"type":"CategoryLabel"}],"created":"2019-08-31T19:23:02.550Z","target":[{"type":"SpecificResource","source":"https://kjc-sv002.kjc.uni-heidelberg.de:8080/fcgi-bin/iipsrv.fcgi?IIIF=imageStorage/ecpo_new/jingbao/1939/04/jb_3796_1939-04-22_0005%252B0008.tif/full/full/0/default.jpg","id":"s-15672793825466","selector":{"value":"<g transform=\"matrix(1 0 0 1 3067.13 355.57)\" id=\"s-15672793825466\">\n<polygon points=\"-68.99,-31.67 68.99,-31.67 68.99,31.67 -68.99,31.67 \"/>\n</g>","type":"SvgSelector"}}],"type":"Annotation","id":"s-1567279382550"},{"body":[{"value":{"color":"purple","name":"additional","label":"Additional Information"},"type":"CategoryLabel"}],"created":"2019-08-31T19:23:05.726Z","target":[{"type":"SpecificResource","source":"https://kjc-sv002.kjc.uni-heidelberg.de:8080/fcgi-bin/iipsrv.fcgi?IIIF=imageStorage/ecpo_new/jingbao/1939/04/jb_3796_1939-04-22_0005%252B0008.tif/full/full/0/default.jpg","id":"s-15672793857223","selector":{"value":"<g transform=\"matrix(1 0 0 1 2761.76 351.73)\" id=\"s-15672793857223\">\n<polygon points=\"-75.78,-32.8 75.78,-32.8 75.78,32.8 -75.78,32.8 \"/>\n</g>","type":"SvgSelector"}}],"type":"Annotation","id":"s-1567279385726"},{"body":[{"value":{"color":"purple","name":"additional","label":"Additional Information"},"type":"CategoryLabel"}],"created":"2019-08-31T19:23:10.440Z","target":[{"type":"SpecificResource","source":"https://kjc-sv002.kjc.uni-heidelberg.de:8080/fcgi-bin/iipsrv.fcgi?IIIF=imageStorage/ecpo_new/jingbao/1939/04/jb_3796_1939-04-22_0005%252B0008.tif/full/full/0/default.jpg","id":"s-15672793904345","selector":{"value":"<g transform=\"matrix(1 0 0 1 3513.29 699.23)\" id=\"s-15672793904345\">\n<polygon points=\"0,0 0,0 0,0 0,0 \"/>\n</g>","type":"SvgSelector"}}],"type":"Annotation","id":"s-1567279390440"},{"body":[{"value":{"color":"purple","name":"additional","label":"Additional Information"},"type":"CategoryLabel"}],"created":"2019-08-31T19:23:25.210Z","target":[{"type":"SpecificResource","source":"https://kjc-sv002.kjc.uni-heidelberg.de:8080/fcgi-bin/iipsrv.fcgi?IIIF=imageStorage/ecpo_new/jingbao/1939/04/jb_3796_1939-04-22_0005%252B0008.tif/full/full/0/default.jpg","id":"s-15672794052030","selector":{"value":"<g transform=\"matrix(1 0 0 1 4374.59 1715.83)\" id=\"s-15672794052030\">\n<polygon points=\"-23.63,-1289.45 48.99,-1289.17 35.17,1288.81 -48.99,1289.45 \"/>\n</g>","type":"SvgSelector"}}],"type":"Annotation","id":"s-1567279405210"},{"body":[{"value":{"color":"purple","name":"additional","label":"Additional Information"},"type":"CategoryLabel"}],"created":"2019-08-31T19:23:49.322Z","target":[{"type":"SpecificResource","source":"https://kjc-sv002.kjc.uni-heidelberg.de:8080/fcgi-bin/iipsrv.fcgi?IIIF=imageStorage/ecpo_new/jingbao/1939/04/jb_3796_1939-04-22_0005%252B0008.tif/full/full/0/default.jpg","id":"s-15672794293185","selector":{"value":"<g transform=\"matrix(1 0 0 1 311.63 1665.58)\" id=\"s-15672794293185\">\n<polygon points=\"-0.95,-1263.54 62.95,-1264.17 6.41,1264.17 -62.95,1263.89 \"/>\n</g>","type":"SvgSelector"}}],"type":"Annotation","id":"s-1567279429322"},{"body":[{"value":{"color":"orange","name":"article","label":"Article"},"type":"CategoryLabel"}],"created":"2019-08-31T19:30:54.741Z","target":[{"type":"SpecificResource","source":"https://kjc-sv002.kjc.uni-heidelberg.de:8080/fcgi-bin/iipsrv.fcgi?IIIF=imageStorage/ecpo_new/jingbao/1939/04/jb_3796_1939-04-22_0005%252B0008.tif/full/full/0/default.jpg","id":"s-15672798547386","selector":{"value":"<g transform=\"matrix(1 0 0 1 4077.8 1076.64)\" id=\"s-15672798547386\">\n<polygon points=\"-110.28,-18.85 110.28,-18.85 110.28,18.85 -110.28,18.85 \"/>\n</g>","type":"SvgSelector"}}],"type":"Annotation","id":"s-1567279854741"},{"body":[{"value":{"color":"orange","name":"article","label":"Article"},"type":"CategoryLabel"}],"created":"2019-09-03T07:05:01.916Z","target":[{"type":"SpecificResource","source":"https://kjc-sv002.kjc.uni-heidelberg.de:8080/fcgi-bin/iipsrv.fcgi?IIIF=imageStorage/ecpo_new/jingbao/1939/04/jb_3796_1939-04-22_0005%252B0008.tif/full/full/0/default.jpg","id":"s-15674943019061","selector":{"value":"<g transform=\"matrix(1 0 0 1 3654.39 596.69)\" id=\"s-15674943019061\">\n<polygon points=\"-174.57,-31.93 174.57,-27.65 172.43,31.93 -174.57,26.9 \"/>\n</g>","type":"SvgSelector"}}],"type":"Annotation","id":"s-1567494301916"},{"body":[{"value":{"color":"orange","name":"article","label":"Article"},"type":"CategoryLabel"}],"created":"2019-09-03T07:05:24.166Z","target":[{"type":"SpecificResource","source":"https://kjc-sv002.kjc.uni-heidelberg.de:8080/fcgi-bin/iipsrv.fcgi?IIIF=imageStorage/ecpo_new/jingbao/1939/04/jb_3796_1939-04-22_0005%252B0008.tif/full/full/0/default.jpg","id":"s-15674943241611","selector":{"value":"<g transform=\"matrix(1 0 0 1 3653.6 758.1)\" id=\"s-15674943241611\">\n<polygon points=\"-174.44,-117.13 177.48,-113.93 174.27,117.13 -177.49,113.92 \"/>\n</g>","type":"SvgSelector"}}],"type":"Annotation","id":"s-1567494324166"},{"body":[{"value":{"color":"orange","name":"article","label":"Article"},"type":"CategoryLabel"}],"created":"2019-09-03T07:05:55.676Z","target":[{"type":"SpecificResource","source":"https://kjc-sv002.kjc.uni-heidelberg.de:8080/fcgi-bin/iipsrv.fcgi?IIIF=imageStorage/ecpo_new/jingbao/1939/04/jb_3796_1939-04-22_0005%252B0008.tif/full/full/0/default.jpg","id":"s-156749435566610","selector":{"value":"<g transform=\"matrix(1 0 0 1 3286.08 660.22)\" id=\"s-156749435566610\">\n<polygon points=\"-188.79,-212.88 197.35,-210.72 188.8,212.88 -197.35,210.73 \"/>\n</g>","type":"SvgSelector"}}],"type":"Annotation","id":"s-1567494355676"},{"body":[{"value":{"color":"orange","name":"article","label":"Article"},"type":"CategoryLabel"}],"created":"2019-09-03T07:07:04.581Z","target":[{"type":"SpecificResource","source":"https://kjc-sv002.kjc.uni-heidelberg.de:8080/fcgi-bin/iipsrv.fcgi?IIIF=imageStorage/ecpo_new/jingbao/1939/04/jb_3796_1939-04-22_0005%252B0008.tif/full/full/0/default.jpg","id":"s-15674944245768","selector":{"value":"<g transform=\"matrix(1 0 0 1 2775.47 546.24)\" id=\"s-15674944245768\">\n<polygon points=\"-172.22,-103.77 177.56,-102.7 174.36,103.77 -177.56,101.63 \"/>\n</g>","type":"SvgSelector"}}],"type":"Annotation","id":"s-1567494424581"},{"body":[{"value":{"color":"orange","name":"article","label":"Article"},"type":"CategoryLabel"}],"created":"2019-09-03T07:07:29.028Z","target":[{"type":"SpecificResource","source":"https://kjc-sv002.kjc.uni-heidelberg.de:8080/fcgi-bin/iipsrv.fcgi?IIIF=imageStorage/ecpo_new/jingbao/1939/04/jb_3796_1939-04-22_0005%252B0008.tif/full/full/0/default.jpg","id":"s-15674944490232","selector":{"value":"<g transform=\"matrix(1 0 0 1 2772.63 764.08)\" id=\"s-15674944490232\">\n<polygon points=\"-173.82,-102.16 175.96,-101.08 174.89,102.16 -175.96,98.95 \"/>\n</g>","type":"SvgSelector"}}],"type":"Annotation","id":"s-1567494449028"},{"body":[{"value":{"color":"orange","name":"article","label":"Article"},"type":"CategoryLabel"}],"created":"2019-09-03T07:07:54.492Z","target":[{"type":"SpecificResource","source":"https://kjc-sv002.kjc.uni-heidelberg.de:8080/fcgi-bin/iipsrv.fcgi?IIIF=imageStorage/ecpo_new/jingbao/1939/04/jb_3796_1939-04-22_0005%252B0008.tif/full/full/0/default.jpg","id":"s-15674944744883","selector":{"value":"<g transform=\"matrix(1 0 0 1 3765.3 989.63)\" id=\"s-15674944744883\">\n<polygon points=\"-63.65,-103.22 61.51,-101.08 63.65,103.23 -61.51,101.09 \"/>\n</g>","type":"SvgSelector"}}],"type":"Annotation","id":"s-1567494474492"},{"body":[{"value":{"color":"orange","name":"article","label":"Article"},"type":"CategoryLabel"}],"created":"2019-09-03T07:08:35.115Z","target":[{"type":"SpecificResource","source":"https://kjc-sv002.kjc.uni-heidelberg.de:8080/fcgi-bin/iipsrv.fcgi?IIIF=imageStorage/ecpo_new/jingbao/1939/04/jb_3796_1939-04-22_0005%252B0008.tif/full/full/0/default.jpg","id":"s-15674945151106","selector":{"value":"<g transform=\"matrix(1 0 0 1 3566.86 1038.88)\" id=\"s-15674945151106\">\n<polygon points=\"-115.53,-54.55 115.52,-51.34 117.66,54.55 -117.66,52.41 \"/>\n</g>","type":"SvgSelector"}}],"type":"Annotation","id":"s-1567494515115"},{"body":[{"value":{"color":"orange","name":"article","label":"Article"},"type":"CategoryLabel"}],"created":"2019-09-03T07:08:53.217Z","target":[{"type":"SpecificResource","source":"https://kjc-sv002.kjc.uni-heidelberg.de:8080/fcgi-bin/iipsrv.fcgi?IIIF=imageStorage/ecpo_new/jingbao/1939/04/jb_3796_1939-04-22_0005%252B0008.tif/full/full/0/default.jpg","id":"s-15674945332084","selector":{"value":"<g transform=\"matrix(1 0 0 1 3234.11 987.32)\" id=\"s-15674945332084\">\n<polygon points=\"-216.9,-104.14 219.06,-100.34 214.19,104.14 -219.06,100.33 \"/>\n</g>","type":"SvgSelector"}}],"type":"Annotation","id":"s-1567494533217"},{"body":[{"value":{"color":"green","name":"advertisement","label":"Advertisement"},"type":"CategoryLabel"}],"created":"2019-09-03T14:04:35.843Z","target":[{"type":"SpecificResource","source":"https://kjc-sv002.kjc.uni-heidelberg.de:8080/fcgi-bin/iipsrv.fcgi?IIIF=imageStorage/ecpo_new/jingbao/1939/04/jb_3796_1939-04-22_0005%252B0008.tif/full/full/0/default.jpg","id":"s-15675194758321","selector":{"value":"<g transform=\"matrix(1 0 0 1 2788.06 1422.93)\" id=\"s-15675194758321\">\n<polygon points=\"-194.15,-481.97 209.81,-480.49 199.76,481.97 -209.81,476.2 \"/>\n</g>","type":"SvgSelector"}}],"type":"Annotation","id":"s-1567519475843"},{"body":[{"value":{"color":"orange","name":"article","label":"Article"},"type":"CategoryLabel"}],"created":"2019-09-03T14:05:31.231Z","target":[{"type":"SpecificResource","source":"https://kjc-sv002.kjc.uni-heidelberg.de:8080/fcgi-bin/iipsrv.fcgi?IIIF=imageStorage/ecpo_new/jingbao/1939/04/jb_3796_1939-04-22_0005%252B0008.tif/full/full/0/default.jpg","id":"s-15675195312233","selector":{"value":"<g transform=\"matrix(1 0 0 1 4223.76 1443.95)\" id=\"s-15675195312233\">\n<polygon points=\"-74.22,-93.44 76.95,-92.06 74.2,93.45 -76.95,93.45 \"/>\n</g>","type":"SvgSelector"}}],"type":"Annotation","id":"s-1567519531231"},{"body":[{"value":{"color":"orange","name":"article","label":"Article"},"type":"CategoryLabel"}],"created":"2019-09-03T14:05:55.188Z","target":[{"type":"SpecificResource","source":"https://kjc-sv002.kjc.uni-heidelberg.de:8080/fcgi-bin/iipsrv.fcgi?IIIF=imageStorage/ecpo_new/jingbao/1939/04/jb_3796_1939-04-22_0005%252B0008.tif/full/full/0/default.jpg","id":"s-15675195551829","selector":{"value":"<g transform=\"matrix(1 0 0 1 4071.22 1325.28)\" id=\"s-15675195551829\">\n<polygon points=\"-76.73,-214.14 82.22,-212.76 77.63,214.15 -82.22,208.63 \"/>\n</g>","type":"SvgSelector"}}],"type":"Annotation","id":"s-1567519555188"},{"body":[{"value":{"color":"orange","name":"article","label":"Article"},"type":"CategoryLabel"}],"created":"2019-09-03T14:06:14.234Z","target":[{"type":"SpecificResource","source":"https://kjc-sv002.kjc.uni-heidelberg.de:8080/fcgi-bin/iipsrv.fcgi?IIIF=imageStorage/ecpo_new/jingbao/1939/04/jb_3796_1939-04-22_0005%252B0008.tif/full/full/0/default.jpg","id":"s-15675195742308","selector":{"value":"<g transform=\"matrix(1 0 0 1 3920.28 1215.07)\" id=\"s-15675195742308\">\n<polygon points=\"-64.58,-104.44 64.58,-103.06 61.84,104.44 -63.21,103.05 \"/>\n</g>","type":"SvgSelector"}}],"type":"Annotation","id":"s-1567519574234"},{"body":[{"value":{"color":"orange","name":"article","label":"Article"},"type":"CategoryLabel"}],"created":"2019-09-03T14:06:43.462Z","target":[{"type":"SpecificResource","source":"https://kjc-sv002.kjc.uni-heidelberg.de:8080/fcgi-bin/iipsrv.fcgi?IIIF=imageStorage/ecpo_new/jingbao/1939/04/jb_3796_1939-04-22_0005%252B0008.tif/full/full/0/default.jpg","id":"s-15675196034570","selector":{"value":"<g transform=\"matrix(1 0 0 1 3913.79 1435.83)\" id=\"s-15675196034570\">\n<polygon points=\"-60.23,-102.38 64.82,-101 62.07,102.38 -64.82,99.65 \"/>\n</g>","type":"SvgSelector"}}],"type":"Annotation","id":"s-1567519603462"},{"body":[{"value":{"color":"orange","name":"article","label":"Article"},"type":"CategoryLabel"}],"created":"2019-09-03T14:12:46.026Z","target":[{"type":"SpecificResource","source":"https://kjc-sv002.kjc.uni-heidelberg.de:8080/fcgi-bin/iipsrv.fcgi?IIIF=imageStorage/ecpo_new/jingbao/1939/04/jb_3796_1939-04-22_0005%252B0008.tif/full/full/0/default.jpg","id":"s-15675199660227","selector":{"value":"<g transform=\"matrix(1 0 0 1 3545.81 1211.21)\" id=\"s-15675199660227\">\n<polygon points=\"-208.17,-106.5 210.91,-101 208.18,106.5 -210.91,98.25 \"/>\n</g>","type":"SvgSelector"}}],"type":"Annotation","id":"s-1567519966026"},{"body":[{"value":{"color":"orange","name":"article","label":"Article"},"type":"CategoryLabel"}],"created":"2019-09-03T14:13:18.604Z","target":[{"type":"SpecificResource","source":"https://kjc-sv002.kjc.uni-heidelberg.de:8080/fcgi-bin/iipsrv.fcgi?IIIF=imageStorage/ecpo_new/jingbao/1939/04/jb_3796_1939-04-22_0005%252B0008.tif/full/full/0/default.jpg","id":"s-15675199985964","selector":{"value":"<g transform=\"matrix(1 0 0 1 3542.16 1429.94)\" id=\"s-15675199985964\">\n<polygon points=\"-208.19,-104.44 210.94,-100.31 206.81,104.44 -210.94,101.69 \"/>\n</g>","type":"SvgSelector"}}],"type":"Annotation","id":"s-1567519998604"},{"body":[{"value":{"color":"orange","name":"article","label":"Article"},"type":"CategoryLabel"}],"created":"2019-09-03T14:14:07.604Z","target":[{"type":"SpecificResource","source":"https://kjc-sv002.kjc.uni-heidelberg.de:8080/fcgi-bin/iipsrv.fcgi?IIIF=imageStorage/ecpo_new/jingbao/1939/04/jb_3796_1939-04-22_0005%252B0008.tif/full/full/0/default.jpg","id":"s-15675200475984","selector":{"value":"<g transform=\"matrix(1 0 0 1 3192.67 1391.91)\" id=\"s-15675200475984\">\n<polygon points=\"-111.98,-141.53 113.36,-140.16 110.61,141.53 -113.36,138.79 \"/>\n</g>","type":"SvgSelector"}}],"type":"Annotation","id":"s-1567520047604"},{"body":[{"value":{"color":"orange","name":"article","label":"Article"},"type":"CategoryLabel"}],"created":"2019-09-03T14:14:24.048Z","target":[{"type":"SpecificResource","source":"https://kjc-sv002.kjc.uni-heidelberg.de:8080/fcgi-bin/iipsrv.fcgi?IIIF=imageStorage/ecpo_new/jingbao/1939/04/jb_3796_1939-04-22_0005%252B0008.tif/full/full/0/default.jpg","id":"s-15675200640443","selector":{"value":"<g transform=\"matrix(1 0 0 1 3044.95 1316.8)\" id=\"s-15675200640443\">\n<polygon points=\"-32.97,-213.91 33.91,-213 29.78,213.91 -33.91,212.5 \"/>\n</g>","type":"SvgSelector"}}],"type":"Annotation","id":"s-1567520064048"},{"body":[{"value":{"color":"orange","name":"article","label":"Article"},"type":"CategoryLabel"}],"created":"2019-09-03T14:14:56.937Z","target":[{"type":"SpecificResource","source":"https://kjc-sv002.kjc.uni-heidelberg.de:8080/fcgi-bin/iipsrv.fcgi?IIIF=imageStorage/ecpo_new/jingbao/1939/04/jb_3796_1939-04-22_0005%252B0008.tif/full/full/0/default.jpg","id":"s-15675200969325","selector":{"value":"<g transform=\"matrix(1 0 0 1 4141.05 1766.57)\" id=\"s-15675200969325\">\n<polygon points=\"-152.97,-214.37 162.62,-209.34 158.95,214.37 -162.62,213.91 \"/>\n</g>","type":"SvgSelector"}}],"type":"Annotation","id":"s-1567520096937"},{"body":[{"value":{"color":"orange","name":"article","label":"Article"},"type":"CategoryLabel"}],"created":"2019-09-03T14:15:36.675Z","target":[{"type":"SpecificResource","source":"https://kjc-sv002.kjc.uni-heidelberg.de:8080/fcgi-bin/iipsrv.fcgi?IIIF=imageStorage/ecpo_new/jingbao/1939/04/jb_3796_1939-04-22_0005%252B0008.tif/full/full/0/default.jpg","id":"s-156752013666710","selector":{"value":"<g transform=\"matrix(1 0 0 1 3489.26 1652.54)\" id=\"s-156752013666710\">\n<polygon points=\"-483.69,-107.17 485.53,-99.88 482.32,107.17 -485.53,104.42 \"/>\n</g>","type":"SvgSelector"}}],"type":"Annotation","id":"s-1567520136674"},{"body":[{"value":{"color":"orange","name":"article","label":"Article"},"type":"CategoryLabel"}],"created":"2019-09-03T14:16:05.301Z","target":[{"type":"SpecificResource","source":"https://kjc-sv002.kjc.uni-heidelberg.de:8080/fcgi-bin/iipsrv.fcgi?IIIF=imageStorage/ecpo_new/jingbao/1939/04/jb_3796_1939-04-22_0005%252B0008.tif/full/full/0/default.jpg","id":"s-156752016529310","selector":{"value":"<g transform=\"matrix(1 0 0 1 3485.11 1873.03)\" id=\"s-156752016529310\">\n<polygon points=\"-481.66,-104.42 485.27,-102.59 483.89,104.42 -485.27,104.42 \"/>\n</g>","type":"SvgSelector"}}],"type":"Annotation","id":"s-1567520165301"},{"body":[{"value":{"color":"blue","name":"image","label":"Image or Drawing"},"type":"CategoryLabel"}],"created":"2021-07-31T14:24:16.488Z","target":[{"type":"SpecificResource","source":"https://kjc-sv002.kjc.uni-heidelberg.de:8080/fcgi-bin/iipsrv.fcgi?IIIF=imageStorage/ecpo_new/jingbao/1939/04/jb_3796_1939-04-22_0005%252B0008.tif/full/full/0/default.jpg","id":"s-16277414564871","selector":{"value":"<g transform=\"matrix(1 0 0 1 2785.91 1173.1)\" id=\"s-16277414564871\">\n<polygon points=\"-130.45,-148.6 130.45,-148.6 130.45,148.6 -130.45,148.6 \"/>\n</g>","type":"SvgSelector"}}],"type":"Annotation","id":"s-1627741456488"},{"body":[{"value":{"color":"blue","name":"image","label":"Image or Drawing"},"type":"CategoryLabel"}],"created":"2021-07-31T14:21:42.764Z","target":[{"type":"SpecificResource","source":"https://kjc-sv002.kjc.uni-heidelberg.de:8080/fcgi-bin/iipsrv.fcgi?IIIF=imageStorage/ecpo_new/jingbao/1939/04/jb_3796_1939-04-22_0005%252B0008.tif/full/full/0/default.jpg","id":"s-16277413027644","selector":{"value":"<g transform=\"matrix(1 0 0 1 4071.35 752.57)\" id=\"s-16277413027644\">\n<polygon points=\"-211.37,-299.01 211.36,-298.1 211.35,299.01 -207.74,297.19 \"/>\n</g>","type":"SvgSelector"}}],"type":"Annotation","id":"s-1627741302764"},{"body":[{"value":{"color":"green","name":"advertisement","label":"Advertisement"},"type":"CategoryLabel"}],"created":"2019-09-03T15:57:44.673Z","target":[{"type":"SpecificResource","source":"https://kjc-sv002.kjc.uni-heidelberg.de:8080/fcgi-bin/iipsrv.fcgi?IIIF=imageStorage/ecpo_new/jingbao/1939/04/jb_3796_1939-04-22_0005%252B0008.tif/full/full/0/default.jpg","id":"s-15675262646549","selector":{"value":"<g transform=\"matrix(1 0 0 1 3434.71 2529.09)\" id=\"s-15675262646549\">\n<polygon points=\"-843.55,-537.54 855.26,-533.91 844.05,534.45 -855.26,537.54 \"/>\n</g>","type":"SvgSelector"}}],"type":"Annotation","id":"s-1567526264673"},{"body":[{"value":{"color":"green","name":"advertisement","label":"Advertisement"},"type":"CategoryLabel"}],"created":"2019-09-03T16:03:28.906Z","target":[{"type":"SpecificResource","source":"https://kjc-sv002.kjc.uni-heidelberg.de:8080/fcgi-bin/iipsrv.fcgi?IIIF=imageStorage/ecpo_new/jingbao/1939/04/jb_3796_1939-04-22_0005%252B0008.tif/full/full/0/default.jpg","id":"s-15675266088974","selector":{"value":"<g transform=\"matrix(1 0 0 1 2360.47 720.62)\" id=\"s-15675266088974\">\n<polygon points=\"-201.17,-304.23 217.66,-302.58 206.12,304.22 -217.66,302.58 \"/>\n</g>","type":"SvgSelector"}}],"type":"Annotation","id":"s-1567526608906"},{"body":[{"value":{"color":"green","name":"advertisement","label":"Advertisement"},"type":"CategoryLabel"}],"created":"2019-09-03T16:21:30.337Z","target":[{"type":"SpecificResource","source":"https://kjc-sv002.kjc.uni-heidelberg.de:8080/fcgi-bin/iipsrv.fcgi?IIIF=imageStorage/ecpo_new/jingbao/1939/04/jb_3796_1939-04-22_0005%252B0008.tif/full/full/0/default.jpg","id":"s-15675276903266","selector":{"value":"<g transform=\"matrix(1 0 0 1 2331.91 2078.2)\" id=\"s-15675276903266\">\n<polygon points=\"-188.7,-1010.72 225.13,-1007.8 192.53,1010.72 -225.13,1009.81 \"/>\n</g>","type":"SvgSelector"}}],"type":"Annotation","id":"s-1567527690337"},{"body":[{"value":{"color":"blue","name":"image","label":"Image or Drawing"},"type":"CategoryLabel"}],"created":"2019-09-17T18:44:52.947Z","target":[{"type":"SpecificResource","source":"https://kjc-sv002.kjc.uni-heidelberg.de:8080/fcgi-bin/iipsrv.fcgi?IIIF=imageStorage/ecpo_new/jingbao/1939/04/jb_3796_1939-04-22_0005%252B0008.tif/full/full/0/default.jpg","id":"s-15687458929394","selector":{"value":"<g transform=\"matrix(1 0 0 1 2902.44 1653.73)\" id=\"s-15687458929394\">\n<polygon points=\"-78.29,-207.2 78.29,-207.2 78.29,207.2 -78.29,207.2 \"/>\n</g>","type":"SvgSelector"}}],"type":"Annotation","id":"s-1568745892947"},{"body":[{"value":{"color":"blue","name":"image","label":"Image or Drawing"},"type":"CategoryLabel"}],"created":"2019-09-17T18:45:39.029Z","target":[{"type":"SpecificResource","source":"https://kjc-sv002.kjc.uni-heidelberg.de:8080/fcgi-bin/iipsrv.fcgi?IIIF=imageStorage/ecpo_new/jingbao/1939/04/jb_3796_1939-04-22_0005%252B0008.tif/full/full/0/default.jpg","id":"s-15687459390211","selector":{"value":"<g transform=\"matrix(1 0 0 1 2353.14 1155.52)\" id=\"s-15687459390211\">\n<polygon points=\"-185.05,-54.09 185.05,-50.29 181.25,54.09 -185.05,50.29 \"/>\n</g>","type":"SvgSelector"}}],"type":"Annotation","id":"s-1568745939029"},{"body":[{"value":{"color":"blue","name":"image","label":"Image or Drawing"},"type":"CategoryLabel"}],"created":"2019-09-17T18:45:56.823Z","target":[{"type":"SpecificResource","source":"https://kjc-sv002.kjc.uni-heidelberg.de:8080/fcgi-bin/iipsrv.fcgi?IIIF=imageStorage/ecpo_new/jingbao/1939/04/jb_3796_1939-04-22_0005%252B0008.tif/full/full/0/default.jpg","id":"s-15687459568181","selector":{"value":"<g transform=\"matrix(1 0 0 1 2344.6 1579.71)\" id=\"s-15687459568181\">\n<polygon points=\"186,214.47 -186,214.47 -186,-214.47 186,-214.47 \"/>\n</g>","type":"SvgSelector"}}],"type":"Annotation","id":"s-1568745956823"},{"body":[{"value":{"color":"blue","name":"image","label":"Image or Drawing"},"type":"CategoryLabel"}],"created":"2019-09-17T18:46:23.409Z","target":[{"type":"SpecificResource","source":"https://kjc-sv002.kjc.uni-heidelberg.de:8080/fcgi-bin/iipsrv.fcgi?IIIF=imageStorage/ecpo_new/jingbao/1939/04/jb_3796_1939-04-22_0005%252B0008.tif/full/full/0/default.jpg","id":"s-15687459834021","selector":{"value":"<g transform=\"matrix(1 0 0 1 2325.14 2866.85)\" id=\"s-15687459834021\">\n<polygon points=\"190.59,91.74 -190.59,91.74 -190.59,-91.74 190.59,-91.74 \"/>\n</g>","type":"SvgSelector"}}],"type":"Annotation","id":"s-1568745983409"},{"body":[{"value":{"color":"orange","name":"article","label":"Article"},"type":"CategoryLabel"}],"created":"2022-08-15T15:20:20.702Z","target":[{"type":"SpecificResource","source":"https://kjc-sv002.kjc.uni-heidelberg.de:8080/fcgi-bin/iipsrv.fcgi?IIIF=imageStorage/ecpo_new/jingbao/1939/04/jb_3796_1939-04-22_0005%252B0008.tif/full/full/0/default.jpg","id":"s-16605768207001","selector":{"value":"<g transform=\"matrix(1 0 0 1 2075.17 1441.87)\" id=\"s-16605768207001\">\n<polygon points=\"-20.51,-58.18 20.51,-58.18 20.51,58.18 -20.51,58.18 \"/>\n</g>","type":"SvgSelector"}}],"type":"Annotation","id":"s-1660576820702"},{"body":[{"value":{"color":"blue","name":"image","label":"Image or Drawing"},"type":"CategoryLabel"}],"created":"2022-08-15T15:20:18.142Z","target":[{"type":"SpecificResource","source":"https://kjc-sv002.kjc.uni-heidelberg.de:8080/fcgi-bin/iipsrv.fcgi?IIIF=imageStorage/ecpo_new/jingbao/1939/04/jb_3796_1939-04-22_0005%252B0008.tif/full/full/0/default.jpg","id":"s-16605768181408","selector":{"value":"<g transform=\"matrix(1 0 0 1 2077.16 1250.13)\" id=\"s-16605768181408\">\n<polygon points=\"-27.78,-117.69 27.78,-117.69 27.78,117.69 -27.78,117.69 \"/>\n</g>","type":"SvgSelector"}}],"type":"Annotation","id":"s-1660576818142"},{"body":[{"value":{"color":"blue","name":"image","label":"Image or Drawing"},"type":"CategoryLabel"}],"created":"2022-08-15T15:20:13.487Z","target":[{"type":"SpecificResource","source":"https://kjc-sv002.kjc.uni-heidelberg.de:8080/fcgi-bin/iipsrv.fcgi?IIIF=imageStorage/ecpo_new/jingbao/1939/04/jb_3796_1939-04-22_0005%252B0008.tif/full/full/0/default.jpg","id":"s-16605768134857","selector":{"value":"<g transform=\"matrix(1 0 0 1 1910.45 781.73)\" id=\"s-16605768134857\">\n<polygon points=\"-210.36,-236.7 210.36,-236.7 210.36,236.7 -210.36,236.7 \"/>\n</g>","type":"SvgSelector"}}],"type":"Annotation","id":"s-1660576813487"},{"body":[{"value":{"color":"orange","name":"article","label":"Article"},"type":"CategoryLabel"}],"created":"2022-08-15T15:20:06.533Z","target":[{"type":"SpecificResource","source":"https://kjc-sv002.kjc.uni-heidelberg.de:8080/fcgi-bin/iipsrv.fcgi?IIIF=imageStorage/ecpo_new/jingbao/1939/04/jb_3796_1939-04-22_0005%252B0008.tif/full/full/0/default.jpg","id":"s-16605768065329","selector":{"value":"<g transform=\"matrix(1 0 0 1 1624.68 1133.25)\" id=\"s-16605768065329\">\n<polygon points=\"-23.81,-75.37 23.81,-75.37 23.81,75.37 -23.81,75.37 \"/>\n</g>","type":"SvgSelector"}}],"type":"Annotation","id":"s-1660576806533"},{"body":[{"value":{"color":"blue","name":"image","label":"Image or Drawing"},"type":"CategoryLabel"}],"created":"2022-08-15T15:20:02.247Z","target":[{"type":"SpecificResource","source":"https://kjc-sv002.kjc.uni-heidelberg.de:8080/fcgi-bin/iipsrv.fcgi?IIIF=imageStorage/ecpo_new/jingbao/1939/04/jb_3796_1939-04-22_0005%252B0008.tif/full/full/0/default.jpg","id":"s-166057680224410","selector":{"value":"<g transform=\"matrix(1 0 0 1 1639.23 665.14)\" id=\"s-166057680224410\">\n<polygon points=\"-27.78,-112.4 27.78,-112.4 27.78,112.4 -27.78,112.4 \"/>\n</g>","type":"SvgSelector"}}],"type":"Annotation","id":"s-1660576802246"},{"body":[{"value":{"color":"orange","name":"article","label":"Article"},"type":"CategoryLabel"}],"created":"2022-08-15T15:19:56.836Z","target":[{"type":"SpecificResource","source":"https://kjc-sv002.kjc.uni-heidelberg.de:8080/fcgi-bin/iipsrv.fcgi?IIIF=imageStorage/ecpo_new/jingbao/1939/04/jb_3796_1939-04-22_0005%252B0008.tif/full/full/0/default.jpg","id":"s-16605767968343","selector":{"value":"<g transform=\"matrix(1 0 0 1 807.05 978.54)\" id=\"s-16605767968343\">\n<polygon points=\"-18.52,-44.96 18.52,-44.96 18.52,44.96 -18.52,44.96 \"/>\n</g>","type":"SvgSelector"}}],"type":"Annotation","id":"s-1660576796836"},{"body":[{"value":{"color":"orange","name":"article","label":"Article"},"type":"CategoryLabel"}],"created":"2022-08-15T15:19:39.452Z","target":[{"type":"SpecificResource","source":"https://kjc-sv002.kjc.uni-heidelberg.de:8080/fcgi-bin/iipsrv.fcgi?IIIF=imageStorage/ecpo_new/jingbao/1939/04/jb_3796_1939-04-22_0005%252B0008.tif/full/full/0/default.jpg","id":"s-16605767794515","selector":{"value":"<g transform=\"matrix(1 0 0 1 759.42 825.14)\" id=\"s-16605767794515\">\n<polygon points=\"-21.17,-158.68 21.17,-158.68 21.17,158.68 -21.17,158.68 \"/>\n</g>","type":"SvgSelector"}}],"type":"Annotation","id":"s-1660576779452"},{"body":[{"value":{"color":"blue","name":"image","label":"Image or Drawing"},"type":"CategoryLabel"}],"created":"2022-08-15T15:19:35.612Z","target":[{"type":"SpecificResource","source":"https://kjc-sv002.kjc.uni-heidelberg.de:8080/fcgi-bin/iipsrv.fcgi?IIIF=imageStorage/ecpo_new/jingbao/1939/04/jb_3796_1939-04-22_0005%252B0008.tif/full/full/0/default.jpg","id":"s-16605767756116","selector":{"value":"<g transform=\"matrix(1 0 0 1 814.99 694.23)\" id=\"s-16605767756116\">\n<polygon points=\"-26.46,-149.43 26.46,-149.43 26.46,149.43 -26.46,149.43 \"/>\n</g>","type":"SvgSelector"}}],"type":"Annotation","id":"s-1660576775612"},{"body":[{"value":{"color":"blue","name":"image","label":"Image or Drawing"},"type":"CategoryLabel"}],"created":"2022-08-15T15:19:31.464Z","target":[{"type":"SpecificResource","source":"https://kjc-sv002.kjc.uni-heidelberg.de:8080/fcgi-bin/iipsrv.fcgi?IIIF=imageStorage/ecpo_new/jingbao/1939/04/jb_3796_1939-04-22_0005%252B0008.tif/full/full/0/default.jpg","id":"s-16605767714620","selector":{"value":"<g transform=\"matrix(1 0 0 1 886.43 629.44)\" id=\"s-16605767714620\">\n<polygon points=\"-34.4,-161.33 34.4,-161.33 34.4,161.33 -34.4,161.33 \"/>\n</g>","type":"SvgSelector"}}],"type":"Annotation","id":"s-1660576771464"},{"body":[{"color":"#ff7043","width":485.6700000000001,"left":2596.17,"height":424.77,"top":441.97,"type":"GroupAnnotation","id":"s-16605769767746"},{"value":{"color":"","name":"article","label":""},"type":"CategoryLabel"}],"created":"2022-08-15T15:22:56.774Z","target":[{"type":"SpecificResource","source":"https://kjc-sv002.kjc.uni-heidelberg.de:8080/fcgi-bin/iipsrv.fcgi?IIIF=imageStorage/ecpo_new/jingbao/1939/04/jb_3796_1939-04-22_0005%252B0008.tif/full/full/0/default.jpg","id":"s-16605768935737","selector":{"value":"<g transform=\"matrix(1 0 0 1 3017.83 652.67)\" id=\"s-16605768935737\">\n<polygon points=\"-56.89,-201.66 63.51,-201.66 63.51,200.34 -63.51,201.66 \"/>\n</g>","type":"SvgSelector"}},{"type":"SpecificResource","source":"https://kjc-sv002.kjc.uni-heidelberg.de:8080/fcgi-bin/iipsrv.fcgi?IIIF=imageStorage/ecpo_new/jingbao/1939/04/jb_3796_1939-04-22_0005%252B0008.tif/full/full/0/default.jpg","id":"s-15674944245768","selector":{"value":"<g transform=\"matrix(1 0 0 1 2775.47 546.24)\" id=\"s-15674944245768\">\n<polygon points=\"-172.22,-103.77 177.56,-102.7 174.36,103.77 -177.56,101.63 \"/>\n</g>","type":"SvgSelector"}},{"type":"SpecificResource","source":"https://kjc-sv002.kjc.uni-heidelberg.de:8080/fcgi-bin/iipsrv.fcgi?IIIF=imageStorage/ecpo_new/jingbao/1939/04/jb_3796_1939-04-22_0005%252B0008.tif/full/full/0/default.jpg","id":"s-15674944490232","selector":{"value":"<g transform=\"matrix(1 0 0 1 2772.63 764.08)\" id=\"s-15674944490232\">\n<polygon points=\"-173.82,-102.16 175.96,-101.08 174.89,102.16 -175.96,98.95 \"/>\n</g>","type":"SvgSelector"}}],"type":"Annotation","id":"s-16605769767746"},{"body":[{"color":"#ff7043","width":423.72999999999956,"left":3859.4799999999996,"height":642.9300000000003,"top":453.05999999999995,"type":"GroupAnnotation","id":"s-16559218784961"},{"value":{"color":"","name":"article","label":""},"type":"CategoryLabel"}],"created":"2022-06-22T18:17:58.496Z","target":[{"type":"SpecificResource","source":"https://kjc-sv002.kjc.uni-heidelberg.de:8080/fcgi-bin/iipsrv.fcgi?IIIF=imageStorage/ecpo_new/jingbao/1939/04/jb_3796_1939-04-22_0005%252B0008.tif/full/full/0/default.jpg","id":"s-16277413027644","selector":{"value":"<g transform=\"matrix(1 0 0 1 4071.34 752.57)\" id=\"s-16277413027644\">\n<polygon points=\"-211.37,-299.01 211.37,-298.1 211.35,299.01 -207.74,297.19 \"/>\n</g>","type":"SvgSelector"}},{"type":"SpecificResource","source":"https://kjc-sv002.kjc.uni-heidelberg.de:8080/fcgi-bin/iipsrv.fcgi?IIIF=imageStorage/ecpo_new/jingbao/1939/04/jb_3796_1939-04-22_0005%252B0008.tif/full/full/0/default.jpg","id":"s-15672798547386","selector":{"value":"<g transform=\"matrix(1 0 0 1 4077.8 1076.64)\" id=\"s-15672798547386\">\n<polygon points=\"-110.28,-18.85 110.28,-18.85 110.28,18.85 -110.28,18.85 \"/>\n</g>","type":"SvgSelector"}}],"type":"Annotation","id":"s-16559218784961"},{"body":[{"color":"#fff176","width":436.3199999999997,"left":2142.31,"height":609.45,"top":415.8899999999999,"type":"GroupAnnotation","id":"s-16559218713165"},{"value":{"color":"","name":"advertisement","label":""},"type":"CategoryLabel"}],"created":"2022-06-22T18:17:51.317Z","target":[{"type":"SpecificResource","source":"https://kjc-sv002.kjc.uni-heidelberg.de:8080/fcgi-bin/iipsrv.fcgi?IIIF=imageStorage/ecpo_new/jingbao/1939/04/jb_3796_1939-04-22_0005%252B0008.tif/full/full/0/default.jpg","id":"s-15675266088974","selector":{"value":"<g transform=\"matrix(1 0 0 1 2360.47 720.61)\" id=\"s-15675266088974\">\n<polygon points=\"-201.17,-304.23 217.66,-302.57 206.12,304.23 -217.66,302.58 \"/>\n</g>","type":"SvgSelector"}}],"type":"Annotation","id":"s-16559218713165"},{"body":[{"color":"#e6ee9c","width":645.0999999999999,"left":382.89000000000004,"height":386.4000000000001,"top":1564.8,"type":"GroupAnnotation","id":"s-16559218673755"},{"value":{"color":"","name":"article","label":""},"type":"CategoryLabel"}],"created":"2022-06-22T18:17:47.376Z","target":[{"type":"SpecificResource","source":"https://kjc-sv002.kjc.uni-heidelberg.de:8080/fcgi-bin/iipsrv.fcgi?IIIF=imageStorage/ecpo_new/jingbao/1939/04/jb_3796_1939-04-22_0005%252B0008.tif/full/full/0/default.jpg","id":"s-156727888609210","selector":{"value":"<g transform=\"matrix(1 0 0 1 705.44 1758)\" id=\"s-156727888609210\">\n<polygon points=\"-318.22,-192.7 322.05,-187.77 317.99,192.7 -322.05,187.08 \"/>\n</g>","type":"SvgSelector"}}],"type":"Annotation","id":"s-16559218673755"},{"body":[{"color":"#ffa726","width":743.3499999999999,"left":3088.23,"height":428.8899999999999,"top":446.84000000000015,"type":"GroupAnnotation","id":"s-16605769745616"},{"value":{"color":"","name":"article","label":""},"type":"CategoryLabel"}],"created":"2022-08-15T15:22:54.561Z","target":[{"type":"SpecificResource","source":"https://kjc-sv002.kjc.uni-heidelberg.de:8080/fcgi-bin/iipsrv.fcgi?IIIF=imageStorage/ecpo_new/jingbao/1939/04/jb_3796_1939-04-22_0005%252B0008.tif/full/full/0/default.jpg","id":"s-16605768881498","selector":{"value":"<g transform=\"matrix(1 0 0 1 3655.53 510.43)\" id=\"s-16605768881498\">\n<polygon points=\"-117.75,-40.99 117.75,-40.99 117.75,40.99 -117.75,40.99 \"/>\n</g>","type":"SvgSelector"}},{"type":"SpecificResource","source":"https://kjc-sv002.kjc.uni-heidelberg.de:8080/fcgi-bin/iipsrv.fcgi?IIIF=imageStorage/ecpo_new/jingbao/1939/04/jb_3796_1939-04-22_0005%252B0008.tif/full/full/0/default.jpg","id":"s-15674943019061","selector":{"value":"<g transform=\"matrix(1 0 0 1 3654.39 596.69)\" id=\"s-15674943019061\">\n<polygon points=\"-174.57,-31.93 174.57,-27.65 172.43,31.93 -174.57,26.9 \"/>\n</g>","type":"SvgSelector"}},{"type":"SpecificResource","source":"https://kjc-sv002.kjc.uni-heidelberg.de:8080/fcgi-bin/iipsrv.fcgi?IIIF=imageStorage/ecpo_new/jingbao/1939/04/jb_3796_1939-04-22_0005%252B0008.tif/full/full/0/default.jpg","id":"s-15674943241611","selector":{"value":"<g transform=\"matrix(1 0 0 1 3653.59 758.1)\" id=\"s-15674943241611\">\n<polygon points=\"-174.44,-117.13 177.48,-113.93 174.28,117.13 -177.49,113.92 \"/>\n</g>","type":"SvgSelector"}},{"type":"SpecificResource","source":"https://kjc-sv002.kjc.uni-heidelberg.de:8080/fcgi-bin/iipsrv.fcgi?IIIF=imageStorage/ecpo_new/jingbao/1939/04/jb_3796_1939-04-22_0005%252B0008.tif/full/full/0/default.jpg","id":"s-156749435566610","selector":{"value":"<g transform=\"matrix(1 0 0 1 3286.08 660.22)\" id=\"s-156749435566610\">\n<polygon points=\"-188.79,-212.88 197.35,-210.72 188.8,212.88 -197.35,210.73 \"/>\n</g>","type":"SvgSelector"}}],"type":"Annotation","id":"s-16605769745616"},{"body":[{"color":"#ffca28","width":970.81,"left":3014.55,"height":656.03,"top":882.6800000000001,"type":"GroupAnnotation","id":"s-16605769704875"},{"value":{"color":"","name":"article","label":""},"type":"CategoryLabel"}],"created":"2022-08-15T15:22:50.488Z","target":[{"type":"SpecificResource","source":"https://kjc-sv002.kjc.uni-heidelberg.de:8080/fcgi-bin/iipsrv.fcgi?IIIF=imageStorage/ecpo_new/jingbao/1939/04/jb_3796_1939-04-22_0005%252B0008.tif/full/full/0/default.jpg","id":"s-16605769037654","selector":{"value":"<g transform=\"matrix(1 0 0 1 3568.87 934.45)\" id=\"s-16605769037654\">\n<polygon points=\"-114.44,-35.04 114.44,-35.04 114.44,35.04 -114.44,35.04 \"/>\n</g>","type":"SvgSelector"}},{"type":"SpecificResource","source":"https://kjc-sv002.kjc.uni-heidelberg.de:8080/fcgi-bin/iipsrv.fcgi?IIIF=imageStorage/ecpo_new/jingbao/1939/04/jb_3796_1939-04-22_0005%252B0008.tif/full/full/0/default.jpg","id":"s-15674945151106","selector":{"value":"<g transform=\"matrix(1 0 0 1 3566.86 1038.88)\" id=\"s-15674945151106\">\n<polygon points=\"-115.53,-54.55 115.52,-51.34 117.66,54.55 -117.66,52.41 \"/>\n</g>","type":"SvgSelector"}},{"type":"SpecificResource","source":"https://kjc-sv002.kjc.uni-heidelberg.de:8080/fcgi-bin/iipsrv.fcgi?IIIF=imageStorage/ecpo_new/jingbao/1939/04/jb_3796_1939-04-22_0005%252B0008.tif/full/full/0/default.jpg","id":"s-15674945332084","selector":{"value":"<g transform=\"matrix(1 0 0 1 3234.11 987.32)\" id=\"s-15674945332084\">\n<polygon points=\"-216.9,-104.14 219.06,-100.34 214.19,104.14 -219.06,100.33 \"/>\n</g>","type":"SvgSelector"}},{"type":"SpecificResource","source":"https://kjc-sv002.kjc.uni-heidelberg.de:8080/fcgi-bin/iipsrv.fcgi?IIIF=imageStorage/ecpo_new/jingbao/1939/04/jb_3796_1939-04-22_0005%252B0008.tif/full/full/0/default.jpg","id":"s-15674944744883","selector":{"value":"<g transform=\"matrix(1 0 0 1 3765.3 989.63)\" id=\"s-15674944744883\">\n<polygon points=\"-63.65,-103.22 61.51,-101.08 63.65,103.23 -61.51,101.09 \"/>\n</g>","type":"SvgSelector"}},{"type":"SpecificResource","source":"https://kjc-sv002.kjc.uni-heidelberg.de:8080/fcgi-bin/iipsrv.fcgi?IIIF=imageStorage/ecpo_new/jingbao/1939/04/jb_3796_1939-04-22_0005%252B0008.tif/full/full/0/default.jpg","id":"s-15675195742308","selector":{"value":"<g transform=\"matrix(1 0 0 1 3920.28 1215.07)\" id=\"s-15675195742308\">\n<polygon points=\"-64.58,-104.44 64.58,-103.06 61.84,104.44 -63.21,103.05 \"/>\n</g>","type":"SvgSelector"}},{"type":"SpecificResource","source":"https://kjc-sv002.kjc.uni-heidelberg.de:8080/fcgi-bin/iipsrv.fcgi?IIIF=imageStorage/ecpo_new/jingbao/1939/04/jb_3796_1939-04-22_0005%252B0008.tif/full/full/0/default.jpg","id":"s-15675196034570","selector":{"value":"<g transform=\"matrix(1 0 0 1 3913.79 1435.83)\" id=\"s-15675196034570\">\n<polygon points=\"-60.23,-102.38 64.82,-101 62.07,102.38 -64.82,99.65 \"/>\n</g>","type":"SvgSelector"}}],"type":"Annotation","id":"s-16605769704875"},{"body":[{"color":"#fff176","width":326.2399999999998,"left":3977.9300000000003,"height":870.7999999999997,"top":1110.6399999999999,"type":"GroupAnnotation","id":"s-16605769686244"},{"value":{"color":"","name":"article","label":""},"type":"CategoryLabel"}],"created":"2022-08-15T15:22:48.624Z","target":[{"type":"SpecificResource","source":"https://kjc-sv002.kjc.uni-heidelberg.de:8080/fcgi-bin/iipsrv.fcgi?IIIF=imageStorage/ecpo_new/jingbao/1939/04/jb_3796_1939-04-22_0005%252B0008.tif/full/full/0/default.jpg","id":"s-16605769262454","selector":{"value":"<g transform=\"matrix(1 0 0 1 4225.76 1243.46)\" id=\"s-16605769262454\">\n<polygon points=\"-47.63,-66.12 47.63,-66.12 47.63,66.12 -47.63,66.12 \"/>\n</g>","type":"SvgSelector"}},{"type":"SpecificResource","source":"https://kjc-sv002.kjc.uni-heidelberg.de:8080/fcgi-bin/iipsrv.fcgi?IIIF=imageStorage/ecpo_new/jingbao/1939/04/jb_3796_1939-04-22_0005%252B0008.tif/full/full/0/default.jpg","id":"s-15675195551829","selector":{"value":"<g transform=\"matrix(1 0 0 1 4071.22 1325.28)\" id=\"s-15675195551829\">\n<polygon points=\"-76.73,-214.14 82.22,-212.76 77.63,214.15 -82.22,208.63 \"/>\n</g>","type":"SvgSelector"}},{"type":"SpecificResource","source":"https://kjc-sv002.kjc.uni-heidelberg.de:8080/fcgi-bin/iipsrv.fcgi?IIIF=imageStorage/ecpo_new/jingbao/1939/04/jb_3796_1939-04-22_0005%252B0008.tif/full/full/0/default.jpg","id":"s-15675195312233","selector":{"value":"<g transform=\"matrix(1 0 0 1 4223.76 1443.95)\" id=\"s-15675195312233\">\n<polygon points=\"-74.22,-93.44 76.95,-92.06 74.2,93.45 -76.95,93.45 \"/>\n</g>","type":"SvgSelector"}},{"type":"SpecificResource","source":"https://kjc-sv002.kjc.uni-heidelberg.de:8080/fcgi-bin/iipsrv.fcgi?IIIF=imageStorage/ecpo_new/jingbao/1939/04/jb_3796_1939-04-22_0005%252B0008.tif/full/full/0/default.jpg","id":"s-15675200969325","selector":{"value":"<g transform=\"matrix(1 0 0 1 4141.05 1766.57)\" id=\"s-15675200969325\">\n<polygon points=\"-152.97,-214.37 162.62,-209.34 158.95,214.37 -162.62,213.91 \"/>\n</g>","type":"SvgSelector"}}],"type":"Annotation","id":"s-16605769686244"},{"body":[{"color":"#e6ee9c","width":502.60000000000036,"left":3330.72,"height":430.6700000000001,"top":1104.21,"type":"GroupAnnotation","id":"s-16605769656231"},{"value":{"color":"","name":"article","label":""},"type":"CategoryLabel"}],"created":"2022-08-15T15:22:45.623Z","target":[{"type":"SpecificResource","source":"https://kjc-sv002.kjc.uni-heidelberg.de:8080/fcgi-bin/iipsrv.fcgi?IIIF=imageStorage/ecpo_new/jingbao/1939/04/jb_3796_1939-04-22_0005%252B0008.tif/full/full/0/default.jpg","id":"s-16605769223979","selector":{"value":"<g transform=\"matrix(1 0 0 1 3802.39 1322.14)\" id=\"s-16605769223979\">\n<polygon points=\"-30.43,-172.57 30.43,-172.57 30.43,172.57 -30.43,172.57 \"/>\n</g>","type":"SvgSelector"}},{"type":"SpecificResource","source":"https://kjc-sv002.kjc.uni-heidelberg.de:8080/fcgi-bin/iipsrv.fcgi?IIIF=imageStorage/ecpo_new/jingbao/1939/04/jb_3796_1939-04-22_0005%252B0008.tif/full/full/0/default.jpg","id":"s-15675199660227","selector":{"value":"<g transform=\"matrix(1 0 0 1 3545.81 1211.21)\" id=\"s-15675199660227\">\n<polygon points=\"-208.17,-106.5 210.91,-101 208.18,106.5 -210.91,98.25 \"/>\n</g>","type":"SvgSelector"}},{"type":"SpecificResource","source":"https://kjc-sv002.kjc.uni-heidelberg.de:8080/fcgi-bin/iipsrv.fcgi?IIIF=imageStorage/ecpo_new/jingbao/1939/04/jb_3796_1939-04-22_0005%252B0008.tif/full/full/0/default.jpg","id":"s-15675199985964","selector":{"value":"<g transform=\"matrix(1 0 0 1 3542.16 1429.94)\" id=\"s-15675199985964\">\n<polygon points=\"-208.19,-104.44 210.94,-100.31 206.81,104.44 -210.94,101.69 \"/>\n</g>","type":"SvgSelector"}}],"type":"Annotation","id":"s-16605769656231"},{"body":[{"color":"#aed581","width":975.9499999999998,"left":2999.34,"height":875.5600000000002,"top":1102.3899999999999,"type":"GroupAnnotation","id":"s-16605769617903"},{"value":{"color":"","name":"article","label":""},"type":"CategoryLabel"}],"created":"2022-08-15T15:22:41.791Z","target":[{"type":"SpecificResource","source":"https://kjc-sv002.kjc.uni-heidelberg.de:8080/fcgi-bin/iipsrv.fcgi?IIIF=imageStorage/ecpo_new/jingbao/1939/04/jb_3796_1939-04-22_0005%252B0008.tif/full/full/0/default.jpg","id":"s-16605769157569","selector":{"value":"<g transform=\"matrix(1 0 0 1 3195.78 1197.18)\" id=\"s-16605769157569\">\n<polygon points=\"-117.09,-33.06 117.09,-33.06 117.09,33.06 -117.09,33.06 \"/>\n</g>","type":"SvgSelector"}},{"type":"SpecificResource","source":"https://kjc-sv002.kjc.uni-heidelberg.de:8080/fcgi-bin/iipsrv.fcgi?IIIF=imageStorage/ecpo_new/jingbao/1939/04/jb_3796_1939-04-22_0005%252B0008.tif/full/full/0/default.jpg","id":"s-15675200475984","selector":{"value":"<g transform=\"matrix(1 0 0 1 3192.67 1391.91)\" id=\"s-15675200475984\">\n<polygon points=\"-111.98,-141.53 113.36,-140.16 110.61,141.53 -113.36,138.79 \"/>\n</g>","type":"SvgSelector"}},{"type":"SpecificResource","source":"https://kjc-sv002.kjc.uni-heidelberg.de:8080/fcgi-bin/iipsrv.fcgi?IIIF=imageStorage/ecpo_new/jingbao/1939/04/jb_3796_1939-04-22_0005%252B0008.tif/full/full/0/default.jpg","id":"s-16605769115256","selector":{"value":"<g transform=\"matrix(1 0 0 1 3193.79 1141.64)\" id=\"s-16605769115256\">\n<polygon points=\"-101.87,-23.8 101.87,-23.8 101.87,23.8 -101.87,23.8 \"/>\n</g>","type":"SvgSelector"}},{"type":"SpecificResource","source":"https://kjc-sv002.kjc.uni-heidelberg.de:8080/fcgi-bin/iipsrv.fcgi?IIIF=imageStorage/ecpo_new/jingbao/1939/04/jb_3796_1939-04-22_0005%252B0008.tif/full/full/0/default.jpg","id":"s-15675200640443","selector":{"value":"<g transform=\"matrix(1 0 0 1 3044.95 1316.8)\" id=\"s-15675200640443\">\n<polygon points=\"-32.97,-213.91 33.91,-213 29.78,213.91 -33.91,212.5 \"/>\n</g>","type":"SvgSelector"}},{"type":"SpecificResource","source":"https://kjc-sv002.kjc.uni-heidelberg.de:8080/fcgi-bin/iipsrv.fcgi?IIIF=imageStorage/ecpo_new/jingbao/1939/04/jb_3796_1939-04-22_0005%252B0008.tif/full/full/0/default.jpg","id":"s-156752016529310","selector":{"value":"<g transform=\"matrix(1 0 0 1 3485.11 1873.03)\" id=\"s-156752016529310\">\n<polygon points=\"-481.66,-104.42 485.27,-102.59 483.89,104.42 -485.27,104.42 \"/>\n</g>","type":"SvgSelector"}},{"type":"SpecificResource","source":"https://kjc-sv002.kjc.uni-heidelberg.de:8080/fcgi-bin/iipsrv.fcgi?IIIF=imageStorage/ecpo_new/jingbao/1939/04/jb_3796_1939-04-22_0005%252B0008.tif/full/full/0/default.jpg","id":"s-156752013666710","selector":{"value":"<g transform=\"matrix(1 0 0 1 3489.26 1652.54)\" id=\"s-156752013666710\">\n<polygon points=\"-483.69,-107.17 485.53,-99.88 482.32,107.17 -485.53,104.42 \"/>\n</g>","type":"SvgSelector"}}],"type":"Annotation","id":"s-16605769617903"},{"body":[{"color":"#66bb6a","width":628.4200000000001,"left":357.16000000000014,"height":1097.3,"top":1971.99,"type":"GroupAnnotation","id":"s-16605769577285"},{"value":{"color":"","name":"image","label":""},"type":"CategoryLabel"}],"created":"2022-08-15T15:22:37.729Z","target":[{"type":"SpecificResource","source":"https://kjc-sv002.kjc.uni-heidelberg.de:8080/fcgi-bin/iipsrv.fcgi?IIIF=imageStorage/ecpo_new/jingbao/1939/04/jb_3796_1939-04-22_0005%252B0008.tif/full/full/0/default.jpg","id":"s-16605768610533","selector":{"value":"<g transform=\"matrix(1 0 0 1 689.96 2039.27)\" id=\"s-16605768610533\">\n<polygon points=\"-201.76,-66.78 199.11,-61.49 201.76,66.78 -201.76,66.78 \"/>\n</g>","type":"SvgSelector"}},{"type":"SpecificResource","source":"https://kjc-sv002.kjc.uni-heidelberg.de:8080/fcgi-bin/iipsrv.fcgi?IIIF=imageStorage/ecpo_new/jingbao/1939/04/jb_3796_1939-04-22_0005%252B0008.tif/full/full/0/default.jpg","id":"s-15672789374050","selector":{"value":"<g transform=\"matrix(1 0 0 1 671.37 2592.09)\" id=\"s-15672789374050\">\n<polygon points=\"-296.67,-476.7 313.71,-473.93 296.53,476.7 -313.71,475.74 \"/>\n</g>","type":"SvgSelector"}}],"type":"Annotation","id":"s-16605769577285"},{"body":[{"value":{"color":"orange","name":"article","label":"Article"},"type":"CategoryLabel"}],"created":"2022-08-15T15:22:06.246Z","target":[{"type":"SpecificResource","source":"https://kjc-sv002.kjc.uni-heidelberg.de:8080/fcgi-bin/iipsrv.fcgi?IIIF=imageStorage/ecpo_new/jingbao/1939/04/jb_3796_1939-04-22_0005%252B0008.tif/full/full/0/default.jpg","id":"s-16605769262454","selector":{"value":"<g transform=\"matrix(1 0 0 1 4225.76 1243.46)\" id=\"s-16605769262454\">\n<polygon points=\"-47.63,-66.12 47.63,-66.12 47.63,66.12 -47.63,66.12 \"/>\n</g>","type":"SvgSelector"}}],"type":"Annotation","id":"s-1660576926246"},{"body":[{"value":{"color":"orange","name":"article","label":"Article"},"type":"CategoryLabel"}],"created":"2022-08-15T15:22:02.398Z","target":[{"type":"SpecificResource","source":"https://kjc-sv002.kjc.uni-heidelberg.de:8080/fcgi-bin/iipsrv.fcgi?IIIF=imageStorage/ecpo_new/jingbao/1939/04/jb_3796_1939-04-22_0005%252B0008.tif/full/full/0/default.jpg","id":"s-16605769223979","selector":{"value":"<g transform=\"matrix(1 0 0 1 3802.39 1322.14)\" id=\"s-16605769223979\">\n<polygon points=\"-30.43,-172.57 30.43,-172.57 30.43,172.57 -30.43,172.57 \"/>\n</g>","type":"SvgSelector"}}],"type":"Annotation","id":"s-1660576922398"},{"body":[{"value":{"color":"orange","name":"article","label":"Article"},"type":"CategoryLabel"}],"created":"2022-08-15T15:21:55.757Z","target":[{"type":"SpecificResource","source":"https://kjc-sv002.kjc.uni-heidelberg.de:8080/fcgi-bin/iipsrv.fcgi?IIIF=imageStorage/ecpo_new/jingbao/1939/04/jb_3796_1939-04-22_0005%252B0008.tif/full/full/0/default.jpg","id":"s-16605769157569","selector":{"value":"<g transform=\"matrix(1 0 0 1 3195.78 1197.18)\" id=\"s-16605769157569\">\n<polygon points=\"-117.09,-33.06 117.09,-33.06 117.09,33.06 -117.09,33.06 \"/>\n</g>","type":"SvgSelector"}}],"type":"Annotation","id":"s-1660576915757"},{"body":[{"value":{"color":"orange","name":"article","label":"Article"},"type":"CategoryLabel"}],"created":"2022-08-15T15:21:51.526Z","target":[{"type":"SpecificResource","source":"https://kjc-sv002.kjc.uni-heidelberg.de:8080/fcgi-bin/iipsrv.fcgi?IIIF=imageStorage/ecpo_new/jingbao/1939/04/jb_3796_1939-04-22_0005%252B0008.tif/full/full/0/default.jpg","id":"s-16605769115256","selector":{"value":"<g transform=\"matrix(1 0 0 1 3193.79 1141.64)\" id=\"s-16605769115256\">\n<polygon points=\"-101.87,-23.8 101.87,-23.8 101.87,23.8 -101.87,23.8 \"/>\n</g>","type":"SvgSelector"}}],"type":"Annotation","id":"s-1660576911526"},{"body":[{"value":{"color":"orange","name":"article","label":"Article"},"type":"CategoryLabel"}],"created":"2022-08-15T15:21:43.766Z","target":[{"type":"SpecificResource","source":"https://kjc-sv002.kjc.uni-heidelberg.de:8080/fcgi-bin/iipsrv.fcgi?IIIF=imageStorage/ecpo_new/jingbao/1939/04/jb_3796_1939-04-22_0005%252B0008.tif/full/full/0/default.jpg","id":"s-16605769037654","selector":{"value":"<g transform=\"matrix(1 0 0 1 3568.87 934.45)\" id=\"s-16605769037654\">\n<polygon points=\"-114.44,-35.04 114.44,-35.04 114.44,35.04 -114.44,35.04 \"/>\n</g>","type":"SvgSelector"}}],"type":"Annotation","id":"s-1660576903766"},{"body":[{"value":{"color":"orange","name":"article","label":"Article"},"type":"CategoryLabel"}],"created":"2022-08-15T15:21:33.574Z","target":[{"type":"SpecificResource","source":"https://kjc-sv002.kjc.uni-heidelberg.de:8080/fcgi-bin/iipsrv.fcgi?IIIF=imageStorage/ecpo_new/jingbao/1939/04/jb_3796_1939-04-22_0005%252B0008.tif/full/full/0/default.jpg","id":"s-16605768935737","selector":{"value":"<g transform=\"matrix(1 0 0 1 3017.83 652.67)\" id=\"s-16605768935737\">\n<polygon points=\"-56.89,-201.66 63.51,-201.66 63.51,200.34 -63.51,201.66 \"/>\n</g>","type":"SvgSelector"}}],"type":"Annotation","id":"s-1660576893574"},{"body":[{"value":{"color":"orange","name":"article","label":"Article"},"type":"CategoryLabel"}],"created":"2022-08-15T15:21:28.150Z","target":[{"type":"SpecificResource","source":"https://kjc-sv002.kjc.uni-heidelberg.de:8080/fcgi-bin/iipsrv.fcgi?IIIF=imageStorage/ecpo_new/jingbao/1939/04/jb_3796_1939-04-22_0005%252B0008.tif/full/full/0/default.jpg","id":"s-16605768881498","selector":{"value":"<g transform=\"matrix(1 0 0 1 3655.53 510.43)\" id=\"s-16605768881498\">\n<polygon points=\"-117.75,-40.99 117.75,-40.99 117.75,40.99 -117.75,40.99 \"/>\n</g>","type":"SvgSelector"}}],"type":"Annotation","id":"s-1660576888150"},{"body":[{"value":{"color":"blue","name":"image","label":"Image or Drawing"},"type":"CategoryLabel"}],"created":"2022-08-15T15:21:01.054Z","target":[{"type":"SpecificResource","source":"https://kjc-sv002.kjc.uni-heidelberg.de:8080/fcgi-bin/iipsrv.fcgi?IIIF=imageStorage/ecpo_new/jingbao/1939/04/jb_3796_1939-04-22_0005%252B0008.tif/full/full/0/default.jpg","id":"s-16605768610533","selector":{"value":"<g transform=\"matrix(1 0 0 1 689.96 2039.27)\" id=\"s-16605768610533\">\n<polygon points=\"-201.76,-66.78 199.11,-61.49 201.76,66.78 -201.76,66.78 \"/>\n</g>","type":"SvgSelector"}}],"type":"Annotation","id":"s-1660576861054"},{"body":[{"value":{"color":"blue","name":"image","label":"Image or Drawing"},"type":"CategoryLabel"}],"created":"2022-08-15T15:20:26.798Z","target":[{"type":"SpecificResource","source":"https://kjc-sv002.kjc.uni-heidelberg.de:8080/fcgi-bin/iipsrv.fcgi?IIIF=imageStorage/ecpo_new/jingbao/1939/04/jb_3796_1939-04-22_0005%252B0008.tif/full/full/0/default.jpg","id":"s-16605768267976","selector":{"value":"<g transform=\"matrix(1 0 0 1 2055.32 1955.86)\" id=\"s-16605768267976\">\n<polygon points=\"-32.41,-150.09 39.03,-150.09 39.03,150.09 -39.03,150.09 \"/>\n</g>","type":"SvgSelector"}}],"type":"Annotation","id":"s-1660576826798"},{"body":[{"color":"#009688","width":685.1500000000001,"left":1412.06,"height":1322.2799999999995,"top":1757.1500000000003,"type":"GroupAnnotation","id":"s-16605769537339"},{"value":{"color":"","name":"article","label":""},"type":"CategoryLabel"}],"created":"2022-08-15T15:22:33.733Z","target":[{"type":"SpecificResource","source":"https://kjc-sv002.kjc.uni-heidelberg.de:8080/fcgi-bin/iipsrv.fcgi?IIIF=imageStorage/ecpo_new/jingbao/1939/04/jb_3796_1939-04-22_0005%252B0008.tif/full/full/0/default.jpg","id":"s-16605768267976","selector":{"value":"<g transform=\"matrix(1 0 0 1 2055.32 1955.86)\" id=\"s-16605768267976\">\n<polygon points=\"-32.41,-150.09 39.03,-150.09 39.03,150.09 -39.03,150.09 \"/>\n</g>","type":"SvgSelector"}},{"type":"SpecificResource","source":"https://kjc-sv002.kjc.uni-heidelberg.de:8080/fcgi-bin/iipsrv.fcgi?IIIF=imageStorage/ecpo_new/jingbao/1939/04/jb_3796_1939-04-22_0005%252B0008.tif/full/full/0/default.jpg","id":"s-15672790373178","selector":{"value":"<g transform=\"matrix(1 0 0 1 1723.95 1865.26)\" id=\"s-15672790373178\">\n<polygon points=\"-291.44,-107.61 293.44,-100.16 290.83,107.61 -293.44,97.92 \"/>\n</g>","type":"SvgSelector"}},{"type":"SpecificResource","source":"https://kjc-sv002.kjc.uni-heidelberg.de:8080/fcgi-bin/iipsrv.fcgi?IIIF=imageStorage/ecpo_new/jingbao/1939/04/jb_3796_1939-04-22_0005%252B0008.tif/full/full/0/default.jpg","id":"s-15672791106472","selector":{"value":"<g transform=\"matrix(1 0 0 1 1719.32 2086.55)\" id=\"s-15672791106472\">\n<polygon points=\"-288.91,-109.41 292.84,-100.14 288.4,109.42 -292.84,102.76 \"/>\n</g>","type":"SvgSelector"}},{"type":"SpecificResource","source":"https://kjc-sv002.kjc.uni-heidelberg.de:8080/fcgi-bin/iipsrv.fcgi?IIIF=imageStorage/ecpo_new/jingbao/1939/04/jb_3796_1939-04-22_0005%252B0008.tif/full/full/0/default.jpg","id":"s-15672790879088","selector":{"value":"<g transform=\"matrix(1 0 0 1 2052.2 2288)\" id=\"s-15672790879088\">\n<polygon points=\"-44.51,-93.59 44.51,-92.28 40.58,93.59 -44.51,92.3 \"/>\n</g>","type":"SvgSelector"}},{"type":"SpecificResource","source":"https://kjc-sv002.kjc.uni-heidelberg.de:8080/fcgi-bin/iipsrv.fcgi?IIIF=imageStorage/ecpo_new/jingbao/1939/04/jb_3796_1939-04-22_0005%252B0008.tif/full/full/0/default.jpg","id":"s-15672792416855","selector":{"value":"<g transform=\"matrix(1 0 0 1 1713.22 2312.58)\" id=\"s-15672792416855\">\n<polygon points=\"-285.46,-106.7 288.46,-98.85 285.84,106.7 -288.46,97.02 \"/>\n</g>","type":"SvgSelector"}},{"type":"SpecificResource","source":"https://kjc-sv002.kjc.uni-heidelberg.de:8080/fcgi-bin/iipsrv.fcgi?IIIF=imageStorage/ecpo_new/jingbao/1939/04/jb_3796_1939-04-22_0005%252B0008.tif/full/full/0/default.jpg","id":"s-15672792635157","selector":{"value":"<g transform=\"matrix(1 0 0 1 1759.43 2530.19)\" id=\"s-15672792635157\">\n<polygon points=\"-332.87,-107.1 333.88,-96.11 329.84,107.1 -333.88,101.97 \"/>\n</g>","type":"SvgSelector"}},{"type":"SpecificResource","source":"https://kjc-sv002.kjc.uni-heidelberg.de:8080/fcgi-bin/iipsrv.fcgi?IIIF=imageStorage/ecpo_new/jingbao/1939/04/jb_3796_1939-04-22_0005%252B0008.tif/full/full/0/default.jpg","id":"s-15672792880194","selector":{"value":"<g transform=\"matrix(1 0 0 1 1752.03 2753.01)\" id=\"s-15672792880194\">\n<polygon points=\"-333.81,-104.72 336.44,-100.8 331.19,104.73 -336.44,103.42 \"/>\n</g>","type":"SvgSelector"}},{"type":"SpecificResource","source":"https://kjc-sv002.kjc.uni-heidelberg.de:8080/fcgi-bin/iipsrv.fcgi?IIIF=imageStorage/ecpo_new/jingbao/1939/04/jb_3796_1939-04-22_0005%252B0008.tif/full/full/0/default.jpg","id":"s-15672793091310","selector":{"value":"<g transform=\"matrix(1 0 0 1 1747.69 2974.85)\" id=\"s-15672793091310\">\n<polygon points=\"-331.2,-104.08 335.13,-101.44 332.51,104.08 -335.13,98.84 \"/>\n</g>","type":"SvgSelector"}}],"type":"Annotation","id":"s-16605769537339"},{"body":[{"color":"#0288d1","width":1276.27,"left":378.91000000000014,"height":2645.27,"top":427.6199999999999,"type":"GroupAnnotation","id":"s-166057694276810"},{"value":{"color":"","name":"article","label":""},"type":"CategoryLabel"}],"created":"2022-08-15T15:22:22.768Z","target":[{"type":"SpecificResource","source":"https://kjc-sv002.kjc.uni-heidelberg.de:8080/fcgi-bin/iipsrv.fcgi?IIIF=imageStorage/ecpo_new/jingbao/1939/04/jb_3796_1939-04-22_0005%252B0008.tif/full/full/0/default.jpg","id":"s-16605767714620","selector":{"value":"<g transform=\"matrix(1 0 0 1 886.43 629.44)\" id=\"s-16605767714620\">\n<polygon points=\"-34.4,-161.33 34.4,-161.33 34.4,161.33 -34.4,161.33 \"/>\n</g>","type":"SvgSelector"}},{"type":"SpecificResource","source":"https://kjc-sv002.kjc.uni-heidelberg.de:8080/fcgi-bin/iipsrv.fcgi?IIIF=imageStorage/ecpo_new/jingbao/1939/04/jb_3796_1939-04-22_0005%252B0008.tif/full/full/0/default.jpg","id":"s-16605767756116","selector":{"value":"<g transform=\"matrix(1 0 0 1 814.99 694.23)\" id=\"s-16605767756116\">\n<polygon points=\"-26.46,-149.43 26.46,-149.43 26.46,149.43 -26.46,149.43 \"/>\n</g>","type":"SvgSelector"}},{"type":"SpecificResource","source":"https://kjc-sv002.kjc.uni-heidelberg.de:8080/fcgi-bin/iipsrv.fcgi?IIIF=imageStorage/ecpo_new/jingbao/1939/04/jb_3796_1939-04-22_0005%252B0008.tif/full/full/0/default.jpg","id":"s-16605767794515","selector":{"value":"<g transform=\"matrix(1 0 0 1 759.42 825.14)\" id=\"s-16605767794515\">\n<polygon points=\"-21.17,-158.68 21.17,-158.68 21.17,158.68 -21.17,158.68 \"/>\n</g>","type":"SvgSelector"}},{"type":"SpecificResource","source":"https://kjc-sv002.kjc.uni-heidelberg.de:8080/fcgi-bin/iipsrv.fcgi?IIIF=imageStorage/ecpo_new/jingbao/1939/04/jb_3796_1939-04-22_0005%252B0008.tif/full/full/0/default.jpg","id":"s-15672724103643","selector":{"value":"<g transform=\"matrix(1 0 0 1 880.96 961.45)\" id=\"s-15672724103643\">\n<polygon points=\"-33.13,-83.78 38.59,-83.78 34.96,83.78 -38.59,82.87 \"/>\n</g>","type":"SvgSelector"}},{"type":"SpecificResource","source":"https://kjc-sv002.kjc.uni-heidelberg.de:8080/fcgi-bin/iipsrv.fcgi?IIIF=imageStorage/ecpo_new/jingbao/1939/04/jb_3796_1939-04-22_0005%252B0008.tif/full/full/0/default.jpg","id":"s-16605767968343","selector":{"value":"<g transform=\"matrix(1 0 0 1 807.05 978.54)\" id=\"s-16605767968343\">\n<polygon points=\"-18.52,-44.96 18.52,-44.96 18.52,44.96 -18.52,44.96 \"/>\n</g>","type":"SvgSelector"}},{"type":"SpecificResource","source":"https://kjc-sv002.kjc.uni-heidelberg.de:8080/fcgi-bin/iipsrv.fcgi?IIIF=imageStorage/ecpo_new/jingbao/1939/04/jb_3796_1939-04-22_0005%252B0008.tif/full/full/0/default.jpg","id":"s-15672724183164","selector":{"value":"<g transform=\"matrix(1 0 0 1 573.98 535.01)\" id=\"s-15672724183164\">\n<polygon points=\"-165.09,-106.9 169.94,-100.86 164.81,106.89 -169.94,99.95 \"/>\n</g>","type":"SvgSelector"}},{"type":"SpecificResource","source":"https://kjc-sv002.kjc.uni-heidelberg.de:8080/fcgi-bin/iipsrv.fcgi?IIIF=imageStorage/ecpo_new/jingbao/1939/04/jb_3796_1939-04-22_0005%252B0008.tif/full/full/0/default.jpg","id":"s-15672724456045","selector":{"value":"<g transform=\"matrix(1 0 0 1 568.85 759.09)\" id=\"s-15672724456045\">\n<polygon points=\"-162.98,-105.38 169.52,-101.45 165.6,105.38 -169.52,98.83 \"/>\n</g>","type":"SvgSelector"}},{"type":"SpecificResource","source":"https://kjc-sv002.kjc.uni-heidelberg.de:8080/fcgi-bin/iipsrv.fcgi?IIIF=imageStorage/ecpo_new/jingbao/1939/04/jb_3796_1939-04-22_0005%252B0008.tif/full/full/0/default.jpg","id":"s-15672724699383","selector":{"value":"<g transform=\"matrix(1 0 0 1 562.46 977.04)\" id=\"s-15672724699383\">\n<polygon points=\"-164.95,-106.04 168.87,-98.18 164.94,106.04 -168.87,96.87 \"/>\n</g>","type":"SvgSelector"}},{"type":"SpecificResource","source":"https://kjc-sv002.kjc.uni-heidelberg.de:8080/fcgi-bin/iipsrv.fcgi?IIIF=imageStorage/ecpo_new/jingbao/1939/04/jb_3796_1939-04-22_0005%252B0008.tif/full/full/0/default.jpg","id":"s-15672724949871","selector":{"value":"<g transform=\"matrix(1 0 0 1 653.23 1198.48)\" id=\"s-15672724949871\">\n<polygon points=\"-258.57,-106.95 262.88,-99.09 257.63,106.95 -262.88,98.3 \"/>\n</g>","type":"SvgSelector"}},{"type":"SpecificResource","source":"https://kjc-sv002.kjc.uni-heidelberg.de:8080/fcgi-bin/iipsrv.fcgi?IIIF=imageStorage/ecpo_new/jingbao/1939/04/jb_3796_1939-04-22_0005%252B0008.tif/full/full/0/default.jpg","id":"s-15672730050628","selector":{"value":"<g transform=\"matrix(1 0 0 1 681.59 1416.67)\" id=\"s-15672730050628\">\n<polygon points=\"-294.54,-105.81 302.18,-99.28 301.09,105.81 -302.18,102.55 \"/>\n</g>","type":"SvgSelector"}},{"type":"SpecificResource","source":"https://kjc-sv002.kjc.uni-heidelberg.de:8080/fcgi-bin/iipsrv.fcgi?IIIF=imageStorage/ecpo_new/jingbao/1939/04/jb_3796_1939-04-22_0005%252B0008.tif/full/full/0/default.jpg","id":"s-15671951137816","selector":{"value":"<g transform=\"matrix(1 0 0 1 1320.18 1419.45)\" id=\"s-15671951137816\">\n<polygon points=\"-334.5,-104.6 334.5,-97.94 331.83,104.61 -333.16,100.62 \"/>\n</g>","type":"SvgSelector"}},{"type":"SpecificResource","source":"https://kjc-sv002.kjc.uni-heidelberg.de:8080/fcgi-bin/iipsrv.fcgi?IIIF=imageStorage/ecpo_new/jingbao/1939/04/jb_3796_1939-04-22_0005%252B0008.tif/full/full/0/default.jpg","id":"s-15672789904283","selector":{"value":"<g transform=\"matrix(1 0 0 1 1344.7 1641.66)\" id=\"s-15672789904283\">\n<polygon points=\"-300.09,-106.43 304.02,-100.41 300.07,106.43 -304.02,97.27 \"/>\n</g>","type":"SvgSelector"}},{"type":"SpecificResource","source":"https://kjc-sv002.kjc.uni-heidelberg.de:8080/fcgi-bin/iipsrv.fcgi?IIIF=imageStorage/ecpo_new/jingbao/1939/04/jb_3796_1939-04-22_0005%252B0008.tif/full/full/0/default.jpg","id":"s-15672790222699","selector":{"value":"<g transform=\"matrix(1 0 0 1 1229.04 1861.13)\" id=\"s-15672790222699\">\n<polygon points=\"-186.43,-104.38 188.25,-102.57 186.03,101.25 -188.25,104.38 \"/>\n</g>","type":"SvgSelector"}},{"type":"SpecificResource","source":"https://kjc-sv002.kjc.uni-heidelberg.de:8080/fcgi-bin/iipsrv.fcgi?IIIF=imageStorage/ecpo_new/jingbao/1939/04/jb_3796_1939-04-22_0005%252B0008.tif/full/full/0/default.jpg","id":"s-15672791320115","selector":{"value":"<g transform=\"matrix(1 0 0 1 1210.86 2080.4)\" id=\"s-15672791320115\">\n<polygon points=\"-202.41,-103.22 203.41,-101.4 200.81,103.22 -203.41,101.41 \"/>\n</g>","type":"SvgSelector"}},{"type":"SpecificResource","source":"https://kjc-sv002.kjc.uni-heidelberg.de:8080/fcgi-bin/iipsrv.fcgi?IIIF=imageStorage/ecpo_new/jingbao/1939/04/jb_3796_1939-04-22_0005%252B0008.tif/full/full/0/default.jpg","id":"s-15672791619163","selector":{"value":"<g transform=\"matrix(1 0 0 1 1203.99 2300.53)\" id=\"s-15672791619163\">\n<polygon points=\"-198.13,-104.72 205.08,-100.8 202.86,104.72 -205.07,96.88 \"/>\n</g>","type":"SvgSelector"}},{"type":"SpecificResource","source":"https://kjc-sv002.kjc.uni-heidelberg.de:8080/fcgi-bin/iipsrv.fcgi?IIIF=imageStorage/ecpo_new/jingbao/1939/04/jb_3796_1939-04-22_0005%252B0008.tif/full/full/0/default.jpg","id":"s-15672791822688","selector":{"value":"<g transform=\"matrix(1 0 0 1 1199.85 2523.26)\" id=\"s-15672791822688\">\n<polygon points=\"-200.95,-104.94 206.18,-102.31 203.96,104.02 -206.18,104.94 \"/>\n</g>","type":"SvgSelector"}},{"type":"SpecificResource","source":"https://kjc-sv002.kjc.uni-heidelberg.de:8080/fcgi-bin/iipsrv.fcgi?IIIF=imageStorage/ecpo_new/jingbao/1939/04/jb_3796_1939-04-22_0005%252B0008.tif/full/full/0/default.jpg","id":"s-15672792032698","selector":{"value":"<g transform=\"matrix(1 0 0 1 1194.74 2748.9)\" id=\"s-15672792032698\">\n<polygon points=\"-200.28,-105.39 206.84,-105.39 204.22,105.39 -206.84,104.08 \"/>\n</g>","type":"SvgSelector"}},{"type":"SpecificResource","source":"https://kjc-sv002.kjc.uni-heidelberg.de:8080/fcgi-bin/iipsrv.fcgi?IIIF=imageStorage/ecpo_new/jingbao/1939/04/jb_3796_1939-04-22_0005%252B0008.tif/full/full/0/default.jpg","id":"s-156727922130010","selector":{"value":"<g transform=\"matrix(1 0 0 1 1190.42 2968.97)\" id=\"s-156727922130010\">\n<polygon points=\"-204.22,-103.42 204.22,-102.1 202.91,103.42 -204.22,102.12 \"/>\n</g>","type":"SvgSelector"}}],"type":"Annotation","id":"s-166057694276810"},{"body":[{"color":"#1565c0","width":742.24,"left":925.27,"height":873.81,"top":433.47,"type":"GroupAnnotation","id":"s-16605769408828"},{"value":{"color":"","name":"article","label":""},"type":"CategoryLabel"}],"created":"2022-08-15T15:22:20.882Z","target":[{"type":"SpecificResource","source":"https://kjc-sv002.kjc.uni-heidelberg.de:8080/fcgi-bin/iipsrv.fcgi?IIIF=imageStorage/ecpo_new/jingbao/1939/04/jb_3796_1939-04-22_0005%252B0008.tif/full/full/0/default.jpg","id":"s-166057680224410","selector":{"value":"<g transform=\"matrix(1 0 0 1 1639.23 665.14)\" id=\"s-166057680224410\">\n<polygon points=\"-27.78,-112.4 27.78,-112.4 27.78,112.4 -27.78,112.4 \"/>\n</g>","type":"SvgSelector"}},{"type":"SpecificResource","source":"https://kjc-sv002.kjc.uni-heidelberg.de:8080/fcgi-bin/iipsrv.fcgi?IIIF=imageStorage/ecpo_new/jingbao/1939/04/jb_3796_1939-04-22_0005%252B0008.tif/full/full/0/default.jpg","id":"s-15672723365060","selector":{"value":"<g transform=\"matrix(1 0 0 1 1267.29 870.38)\" id=\"s-15672723365060\">\n<polygon points=\"-326.83,-436.4 341.52,-433.28 324.61,436.41 -341.52,432.31 \"/>\n</g>","type":"SvgSelector"}},{"type":"SpecificResource","source":"https://kjc-sv002.kjc.uni-heidelberg.de:8080/fcgi-bin/iipsrv.fcgi?IIIF=imageStorage/ecpo_new/jingbao/1939/04/jb_3796_1939-04-22_0005%252B0008.tif/full/full/0/default.jpg","id":"s-16605768065329","selector":{"value":"<g transform=\"matrix(1 0 0 1 1624.68 1133.25)\" id=\"s-16605768065329\">\n<polygon points=\"-23.81,-75.37 23.81,-75.37 23.81,75.37 -23.81,75.37 \"/>\n</g>","type":"SvgSelector"}}],"type":"Annotation","id":"s-16605769408828"},{"body":[{"color":"#283593","width":421.72000000000025,"left":1699.5900000000001,"height":647.04,"top":445.3600000000001,"type":"GroupAnnotation","id":"s-16605769371733"},{"value":{"color":"","name":"article","label":""},"type":"CategoryLabel"}],"created":"2022-08-15T15:22:17.174Z","target":[{"type":"SpecificResource","source":"https://kjc-sv002.kjc.uni-heidelberg.de:8080/fcgi-bin/iipsrv.fcgi?IIIF=imageStorage/ecpo_new/jingbao/1939/04/jb_3796_1939-04-22_0005%252B0008.tif/full/full/0/default.jpg","id":"s-15671912239394","selector":{"value":"<g transform=\"matrix(1 0 0 1 1911.74 498.64)\" id=\"s-15671912239394\">\n<polygon points=\"-178.55,-52.78 178.54,-51.14 178.54,51.4 -176.94,52.78 \"/>\n</g>","type":"SvgSelector"}},{"type":"SpecificResource","source":"https://kjc-sv002.kjc.uni-heidelberg.de:8080/fcgi-bin/iipsrv.fcgi?IIIF=imageStorage/ecpo_new/jingbao/1939/04/jb_3796_1939-04-22_0005%252B0008.tif/full/full/0/default.jpg","id":"s-16605768134857","selector":{"value":"<g transform=\"matrix(1 0 0 1 1910.45 781.73)\" id=\"s-16605768134857\">\n<polygon points=\"-210.36,-236.7 210.36,-236.7 210.36,236.7 -210.36,236.7 \"/>\n</g>","type":"SvgSelector"}},{"type":"SpecificResource","source":"https://kjc-sv002.kjc.uni-heidelberg.de:8080/fcgi-bin/iipsrv.fcgi?IIIF=imageStorage/ecpo_new/jingbao/1939/04/jb_3796_1939-04-22_0005%252B0008.tif/full/full/0/default.jpg","id":"s-15671912529876","selector":{"value":"<g transform=\"matrix(1 0 0 1 1898.18 1068.71)\" id=\"s-15671912529876\">\n<polygon points=\"-147.93,-23.19 147.92,-21.59 146.34,23.19 -147.93,21.59 \"/>\n</g>","type":"SvgSelector"}}],"type":"Annotation","id":"s-16605769371733"},{"body":[{"color":"#01579b","width":420.6199999999999,"left":2577.75,"height":964.94,"top":940.46,"type":"GroupAnnotation","id":"s-16559219388426"},{"value":{"color":"","name":"advertisement","label":""},"type":"CategoryLabel"}],"created":"2022-06-22T18:18:58.843Z","target":[{"type":"SpecificResource","source":"https://kjc-sv002.kjc.uni-heidelberg.de:8080/fcgi-bin/iipsrv.fcgi?IIIF=imageStorage/ecpo_new/jingbao/1939/04/jb_3796_1939-04-22_0005%252B0008.tif/full/full/0/default.jpg","id":"s-16277414564871","selector":{"value":"<g transform=\"matrix(1 0 0 1 2785.91 1173.1)\" id=\"s-16277414564871\">\n<polygon points=\"-130.45,-148.6 130.45,-148.6 130.45,148.6 -130.45,148.6 \"/>\n</g>","type":"SvgSelector"}},{"type":"SpecificResource","source":"https://kjc-sv002.kjc.uni-heidelberg.de:8080/fcgi-bin/iipsrv.fcgi?IIIF=imageStorage/ecpo_new/jingbao/1939/04/jb_3796_1939-04-22_0005%252B0008.tif/full/full/0/default.jpg","id":"s-15687458929394","selector":{"value":"<g transform=\"matrix(1 0 0 1 2902.44 1653.73)\" id=\"s-15687458929394\">\n<polygon points=\"-78.29,-207.2 78.29,-207.2 78.29,207.2 -78.29,207.2 \"/>\n</g>","type":"SvgSelector"}},{"type":"SpecificResource","source":"https://kjc-sv002.kjc.uni-heidelberg.de:8080/fcgi-bin/iipsrv.fcgi?IIIF=imageStorage/ecpo_new/jingbao/1939/04/jb_3796_1939-04-22_0005%252B0008.tif/full/full/0/default.jpg","id":"s-15675194758321","selector":{"value":"<g transform=\"matrix(1 0 0 1 2788.06 1422.93)\" id=\"s-15675194758321\">\n<polygon points=\"-194.15,-481.97 209.81,-480.49 199.76,481.97 -209.81,476.2 \"/>\n</g>","type":"SvgSelector"}}],"type":"Annotation","id":"s-16559219388426"},{"body":[{"color":"#00838f","width":1711.5200000000004,"left":2578.95,"height":1076.08,"top":1991.0500000000002,"type":"GroupAnnotation","id":"s-16559219411232"},{"value":{"color":"","name":"advertisement","label":""},"type":"CategoryLabel"}],"created":"2022-06-22T18:19:01.123Z","target":[{"type":"SpecificResource","source":"https://kjc-sv002.kjc.uni-heidelberg.de:8080/fcgi-bin/iipsrv.fcgi?IIIF=imageStorage/ecpo_new/jingbao/1939/04/jb_3796_1939-04-22_0005%252B0008.tif/full/full/0/default.jpg","id":"s-15675262646549","selector":{"value":"<g transform=\"matrix(1 0 0 1 3434.71 2529.09)\" id=\"s-15675262646549\">\n<polygon points=\"-843.55,-537.54 855.26,-533.91 844.05,534.45 -855.26,537.54 \"/>\n</g>","type":"SvgSelector"}}],"type":"Annotation","id":"s-16559219411232"},{"body":[{"color":"#43a047","width":451.2600000000002,"left":2106.2799999999997,"height":2022.4400000000003,"top":1066.9799999999998,"type":"GroupAnnotation","id":"s-16559219478528"},{"value":{"color":"","name":"advertisement","label":""},"type":"CategoryLabel"}],"created":"2022-06-22T18:19:07.852Z","target":[{"type":"SpecificResource","source":"https://kjc-sv002.kjc.uni-heidelberg.de:8080/fcgi-bin/iipsrv.fcgi?IIIF=imageStorage/ecpo_new/jingbao/1939/04/jb_3796_1939-04-22_0005%252B0008.tif/full/full/0/default.jpg","id":"s-15687459834021","selector":{"value":"<g transform=\"matrix(1 0 0 1 2325.14 2866.85)\" id=\"s-15687459834021\">\n<polygon points=\"190.59,91.74 -190.59,91.74 -190.59,-91.74 190.59,-91.74 \"/>\n</g>","type":"SvgSelector"}},{"type":"SpecificResource","source":"https://kjc-sv002.kjc.uni-heidelberg.de:8080/fcgi-bin/iipsrv.fcgi?IIIF=imageStorage/ecpo_new/jingbao/1939/04/jb_3796_1939-04-22_0005%252B0008.tif/full/full/0/default.jpg","id":"s-15687459568181","selector":{"value":"<g transform=\"matrix(1 0 0 1 2344.6 1579.71)\" id=\"s-15687459568181\">\n<polygon points=\"186,214.47 -186,214.47 -186,-214.47 186,-214.47 \"/>\n</g>","type":"SvgSelector"}},{"type":"SpecificResource","source":"https://kjc-sv002.kjc.uni-heidelberg.de:8080/fcgi-bin/iipsrv.fcgi?IIIF=imageStorage/ecpo_new/jingbao/1939/04/jb_3796_1939-04-22_0005%252B0008.tif/full/full/0/default.jpg","id":"s-15687459390211","selector":{"value":"<g transform=\"matrix(1 0 0 1 2353.14 1155.52)\" id=\"s-15687459390211\">\n<polygon points=\"-185.05,-54.09 185.05,-50.29 181.25,54.09 -185.05,50.29 \"/>\n</g>","type":"SvgSelector"}},{"type":"SpecificResource","source":"https://kjc-sv002.kjc.uni-heidelberg.de:8080/fcgi-bin/iipsrv.fcgi?IIIF=imageStorage/ecpo_new/jingbao/1939/04/jb_3796_1939-04-22_0005%252B0008.tif/full/full/0/default.jpg","id":"s-15675276903266","selector":{"value":"<g transform=\"matrix(1 0 0 1 2331.91 2078.2)\" id=\"s-15675276903266\">\n<polygon points=\"-188.7,-1010.72 225.13,-1007.8 192.53,1010.72 -225.13,1009.81 \"/>\n</g>","type":"SvgSelector"}}],"type":"Annotation","id":"s-16559219478528"},{"body":[{"value":{"color":"purple","name":"additional","label":"Additional Information"},"type":"CategoryLabel"}],"created":"2022-06-24T08:08:02.169Z","target":[{"type":"SpecificResource","source":"https://kjc-sv002.kjc.uni-heidelberg.de:8080/fcgi-bin/iipsrv.fcgi?IIIF=imageStorage/ecpo_new/jingbao/1939/04/jb_3796_1939-04-22_0005%252B0008.tif/full/full/0/default.jpg","id":"s-165605808216810","selector":{"value":"<g transform=\"matrix(1 0 0 1 3433.96 357.51)\" id=\"s-165605808216810\">\n<polygon points=\"-118.54,-60.21 118.54,-60.21 118.54,60.21 -118.54,60.21 \"/>\n</g>","type":"SvgSelector"}}],"type":"Annotation","id":"s-1656058082169"}],"partOf":{"total":107,"modified":"2022-08-15T17:23:13.769+02:00","id":"http://localhost:8080/exist/apps/ecpo/api/annotations/"},"@context":"http://www.w3.org/ns/anno.jsonld","startIndex":0,"next":"http://localhost:8080/exist/apps/ecpo/api/annotations/?document=https%3A%2F%2Fkjc-sv002.kjc.uni-heidelberg.de%3A8080%2Ffcgi-bin%2Fiipsrv.fcgi%3FIIIF%3DimageStorage%2Fecpo_new%2Fjingbao%2F1939%2F04%2Fjb_3796_1939-04-22_0005%25252B0008.tif%2Ffull%2Ffull%2F0%2Fdefault.jpg&page=0","last":"http://localhost:8080/exist/apps/ecpo/api/annotations/?document=https%3A%2F%2Fkjc-sv002.kjc.uni-heidelberg.de%3A8080%2Ffcgi-bin%2Fiipsrv.fcgi%3FIIIF%3DimageStorage%2Fecpo_new%2Fjingbao%2F1939%2F04%2Fjb_3796_1939-04-22_0005%25252B0008.tif%2Ffull%2Ffull%2F0%2Fdefault.jpg&page=0","type":"AnnotationPage","id":"http://localhost:8080/exist/apps/ecpo/api/annotations/?document=https%3A%2F%2Fkjc-sv002.kjc.uni-heidelberg.de%3A8080%2Ffcgi-bin%2Fiipsrv.fcgi%3FIIIF%3DimageStorage%2Fecpo_new%2Fjingbao%2F1939%2F04%2Fjb_3796_1939-04-22_0005%25252B0008.tif%2Ffull%2Ffull%2F0%2Fdefault.jpg&page=0"}