<?xml version="1.0" encoding="UTF-8"?>
<?xml-model href="https://raw.githubusercontent.com/exc-asia-and-europe/ecpo/master/ecpo.rng" type="application/xml" schematypens="http://relaxng.org/ns/structure/1.0"?>
<!DOCTYPE ecpo [
    <!ENTITY gaiji "&#xe111;">
]>
<fold xml:id="jb_3801_1939-04-27_0002+0003" lastedit="2021-08-16" lasteditor="ysmlouis">
	<!-- start verso page -->
    <div type="page" page="verso" n="2" dir="rtl" mode="vertical-rl">
           <div type="margin" dir="rtl" mode="horizontal-tb">
                  中華民國二十八年四月廿七日　晶報　星期四　第二版<lb/>	
           </div>
           <div type="article">
                  <div>
                         英內閣已决定<lb/>
                         實行强迫兵役<lb/>
                         自十八至廿一歲男子均入伍<lb/>
                         此𦦙在給予各小國充分保障<lb/>
                  </div>
                  <div>
                         <p>
                              （倫敦廿六日海<lb/>
                              通社電）據消息靈<lb/>
                              通人士宣稱、英內<lb/>
                              閣昨日舉行特別會<lb/>
                              議時、决定徵募<lb/>
                              全國自十八至二<lb/>
                              十一歲之男子入伍<lb/>
                              、散會後、首相卽<lb/>
                              赴白金漢宮、謁見<lb/>
                              英王喬治六世、報<lb/>
                              吿內閣此項决議、<lb/>
                              截至此時、關於實<lb/>
                              行强迫兵役之詳細<lb/>
                              內容之官方文吿、<lb/>
                              尚未發表、所可知<lb/>
                              者、英國所以採行<lb/>
                              之者、一方面應<lb/>
                              法國再三之請、另<lb/>
                              一方面以袪除各小<lb/>
                              國對英國兵力不多<lb/>
                              、不足加以援助之<lb/>
                              憂懼、據政府人士<lb/>
                              宣稱、內閣特別會<lb/>
                              議中、全體閣員意<lb/>
                              見一致、外傳某某<lb/>
                              閣員不贊成此項步<lb/>
                              驟之說、幷無根據<lb/>
                              、衆料此項步驟决<lb/>
                              定後、受到影響之<lb/>
                              靑年、當在一百萬<lb/>
                              人附近云、<lb/>
                         </p>
                         <p>
                              （倫敦廿六日路<lb/>
                              透電）英相張伯倫<lb/>
                              、將於今日午後一<lb/>
                              時三刻、（英國夏<lb/>
                              季時刻、）在下院<lb/>
                              宣布强迫軍役之計<lb/>
                              畫、內閣今晨集議<lb/>
                              一時半、散會後英<lb/>
                              國工會總幹事應張<lb/>
                              伯倫之召、赴唐寗<lb/>
                              街十號相邸、聽取<lb/>
                              政府關於强迫軍役<lb/>
                              制之决定、<lb/>
                         </p>
                         <p>
                              （倫敦廿六日哈<lb/>
                              瓦斯電）張伯倫首<lb/>
                              相於本日午前接見<lb/>
                              總工會代表、吿以<lb/>
                              政府决定實施徵兵<lb/>
                              制、全國靑年男子<lb/>
                              、年在二十歲至二<lb/>
                              十一歲之間、除體<lb/>
                              格不適宜者而外、<lb/>
                              共有二十餘萬人、<lb/>
                              均應入伍服役、爲<lb/>
                              期六個月、滿期之<lb/>
                              後、或編入後備軍、<lb/>
                              或編入預備軍、聽<lb/>
                              其自願云、<lb/>
                         </p>
                         <p>
                              （倫敦廿六日美<lb/>
                              聯電）今日首相張<lb/>
                              伯倫氏、在下院中<lb/>
                              發表、英國徵兵制<lb/>
                              之計劃、<lb/>
                         </p>
                  </div>
           </div>
           <div type="article">
                  <div>
                         英法蘇與土耳其合作<lb/>
                         反侵略陣線增强<lb/>
                         傳蘇聯對案範圍較前廣大<lb/>
                  </div>
                  <div>
                         <p>
                              （巴黎廿六日海<lb/>
                              通電）關於法國邀<lb/>
                              請土耳其、加入反<lb/>
                              侵略公約之最近動<lb/>
                              態、極爲此間各國<lb/>
                              外交使節所注意、<lb/>
                              今晨外交當局、曾<lb/>
                              明白表示、英法與<lb/>
                              土耳其進行中之軍<lb/>
                              事合作談判、雖極<lb/>
                              圓滿、且已談至相<lb/>
                              當眉目、但尚不能<lb/>
                              表示如政界人士之<lb/>
                              樂觀、關於蘇聯外<lb/>
                              交副委員長波丹金<lb/>
                              突然離開莫斯私、<lb/>
                              前往土耳其京城一<lb/>
                              事、此間人士咸極<lb/>
                              重視、認爲此乃開<lb/>
                              拓局勢之新要素、<lb/>
                              據悉、英國此次拉<lb/>
                              攏蘇聯、使之玉成<lb/>
                              土耳其加入民主國<lb/>
                              家陣線、無非欲增<lb/>
                              强反極權國家之陣<lb/>
                              容云、<lb/>
                         </p>
                         <p>
                              （巴黎廿五日路<lb/>
                              透電）蘇聯對案內<lb/>
                              容、官方保守秘密<lb/>
                              、惟此間確悉、該<lb/>
                              對案未涉及遠東、<lb/>
                              但其範圍較英法原<lb/>
                              提建議僅涉及土羅<lb/>
                              波三國者爲廣大、<lb/>
                         </p>
                  </div>
            </div>
            <div type="article">
                   <div>
                          蘇波<lb/>
                          邦交<lb/>
                          進步<lb/>
                   </div>
                   <div>
                          <p>
                               （華沙廿<lb/>
                               六日哈瓦<lb/>
                               斯電）外<lb/>
                               交部發言人、頃向<lb/>
                               各報發表談話稱、<lb/>
                               「波蘭與蘇俄兩國<lb/>
                               邦交演進情形、深<lb/>
                               堪滿意」、而波蘭<lb/>
                               利益之所在、蘇俄<lb/>
                               當局予以充分諒解<lb/>
                               、尤足欣慰云、<lb/>
                          </p>
                   </div>
            </div>
            <div type="article">
                   <div>
                          蘇外<lb/>
                          次赴<lb/>
                          保土<lb/>
                   </div>
                   <div>
                          <p>
                               （保加利<lb/>
                               亞國京城<lb/>
                               廿六日電<lb/>
                               ）蘇俄外交委員會<lb/>
                               副委員長波丹金、<lb/>
                               今晨七時到達此間<lb/>
                               、由外交部派代表<lb/>
                               在車站歡迎、中午<lb/>
                               與內閣總理兼外交<lb/>
                               部長古賽伐諾夫晤<lb/>
                               談、午後四時二十<lb/>
                               分賡續行程、前往<lb/>
                               土耳其國京城、<lb/>
                          </p>
                   </div>
            </div>
            <div type="article">
                   <div>
                          法波<lb/>
                          進行<lb/>
                          談話<lb/>
                   </div>
                   <div>
                          <p>
                               （巴黎廿<lb/>
                               六日海通<lb/>
                               電）法國<lb/>
                               公共工程部長孟齊<lb/>
                               、前以主持波蘭<lb/>
                               上西利西亞鐵道通<lb/>
                               車事、行抵華波<lb/>
                               後業已多日、聞日<lb/>
                               來正與波蘭政府各<lb/>
                               閣員進行談話、今<lb/>
                               晨巴黎各報對之咸<lb/>
                               畀以重大意義、據<lb/>
                               稱、孟齊曾與波蘭<lb/>
                               總參謀長史密格萊<lb/>
                               上將、就法波兩國<lb/>
                               在戰時之軍事合作<lb/>
                               問題、加以多方面<lb/>
                               之討論、<lb/>
                          </p>
                   </div>
            </div>
            <div type="article">
                   <div>
                          波利維亞<lb/>
                          實行獨裁<lb/>
                   </div>
                   <div>
                          <p>
                               （波利維亞京城<lb/>
                               廿六日海通電）波<lb/>
                               利維亞總統白熙、<lb/>
                               藉軍人之擁護、解<lb/>
                               散議會、樹立獨裁<lb/>
                               政制後、並未招致<lb/>
                               任何混亂結果、據<lb/>
                               悉、國家政務、現<lb/>
                               暫時仍由內閣洽理<lb/>
                               、同時白熙總統、<lb/>
                               擬在最短期內、實<lb/>
                               行總選舉、白熙總<lb/>
                               統、昨日發表如下<lb/>
                               之文吿稱、「余此<lb/>
                               次突然解散議會、<lb/>
                               、宣佈樹立獨裁政<lb/>
                               制、其動機乃鑒於<lb/>
                               國政之腐敗、官吏<lb/>
                               私利心重、愛國心<lb/>
                               輕、故遂出此斷然<lb/>
                               手段」云、<lb/>
                          </p>
                   </div>
            </div>
            <div type="article">
                   <div>
                          侵略者必潰滅<lb/>
                          －－本文接第一版－－<lb/>
                   </div>
                   <div>
                          <p>
                               又據熟悉國際問<lb/>
                               題者稱、如果歐戰<lb/>
                               不致發生、則德國<lb/>
                               或能對日作物質上<lb/>
                               之援助、以補精神<lb/>
                               援助之不足、但如<lb/>
                               果歐戰發生、則日<lb/>
                               本軍火原料之獲取<lb/>
                               、卽將發生困難、<lb/>
                               但在中國反而有利<lb/>
                               、屆時蘇俄對華必<lb/>
                               將一變其消極之同<lb/>
                               盟關係、而爲積極<lb/>
                               之同盟關係也、又<lb/>
                               據<lb/>
                          </p>
                   </div>
                   <div>   
                          、中國金融<lb/>
                   </div>
                   <div>
                          <p>
                               界方面稱、英國<lb/>
                               如能解决歐戰問題<lb/>
                               之後、卽將進而獲<lb/>
                               取中日問題之解决<lb/>
                               、蓋因英國在財政<lb/>
                               上、借欵上、及貨<lb/>
                               幣平衡上、對華曾<lb/>
                               有極大之援助、而<lb/>
                               尚未眞正開罪日本<lb/>
                               、故其調人資格、<lb/>
                               極合羅輯、英美極<lb/>
                               願盡力援助中國、<lb/>
                               使中國能延長其對<lb/>
                               日抗戰、藉以促進<lb/>
                               和平之可能、惟在<lb/>
                          </p>
                   </div>
                   <div>  
                          相當期間<lb/>
                   </div>
                   <div>
                          <p>
                               能直<!-- character shows font-dependent variations, char found here: ⿺𠃊𥃭 -->接出面干涉<lb/>
                               者、必爲英國、蓋<lb/>
                               其出而干涉之原因<lb/>
                               、非爲中國之同盟<lb/>
                               、實以中立國之立<lb/>
                               場出之也、是以將<lb/>
                               來之中日和平問題<lb/>
                               、實將由於英國之<lb/>
                               出面斡旋、而最近<lb/>
                               英國駐日大使、與<lb/>
                               駐華大使之會晤、<lb/>
                               實爲英國調解遠東<lb/>
                               問題之一種徵兆而<lb/>
                               已、至於召集、<lb/>
                          </p>
                   </div>
                   <div>  
                          遠東會議<lb/>
                   </div>
                   <div>
                          <p>
                               以資解决遠東糾<lb/>
                               紛、日本必將反對、<lb/>
                               因日人之外交天才<lb/>
                               不及中國、故彼等<lb/>
                               反對會議式之調解<lb/>
                               也、目前英國之態<lb/>
                               度、旣不願使日獲<lb/>
                               勝、但亦不願中國<lb/>
                               完全獲勝、彼等之<lb/>
                               政策、無非使中國<lb/>
                               在遠東方面與日本<lb/>
                               作戰、在此時期、<lb/>
                               彼等雖以充分借欵<lb/>
                               給予中國、但在中<lb/>
                               國方面、固可藉此<lb/>
                               獲得商業上經濟上<lb/>
                               及原料獲得上之利<lb/>
                               益也、<lb/>
                          </p>
                   </div>
            </div>
		<div type="article">
                   <div dir="rtl" mode="horizontal-tb">
                          日政府决定<lb/>
                   </div>
                   <div>
                          向滬租界工部局<lb/>
                          要求改組<lb/>
                          不承認一切協定<lb/>
                          對法租界考慮中<lb/>
                   </div>
                   <div>
                          <p>
                               （東京廿六日路透電）據朝日新聞載<lb/>
                               稱、日外相有田、不久卽將請求英美合<lb/>
                               作、以實行日本、對於上海公共租界所<lb/>
                               施之公允正直<!-- ⿺𠃊𥃭 -->的政策、該報續稱、日政<lb/>
                               府已切實决定、維持不承認第三列强、<lb/>
                               與蔣介石所領導政府間、現有一切關於<lb/>
                               公共租界協定之原則、日政府根據此項<lb/>
                               原則、將竭力設法解决各種重大之懸案<lb/>
                               、最注意者如（一）改組公共租界之投<lb/>
                               票制度、（二）改組工部局董事會（三<lb/>
                               ）改組公共租界推廣區域之地位、該報<lb/>
                               末稱、日政府鑒於上海法租界恐怖事件<lb/>
                               之層見疊出、現正愼重考量向法方作同<lb/>
                               樣之交涉云、<lb/>
                          </p> 
                   </div>
            </div>
            <div type="article">
                   <div>
                          在日本旅客<lb/>
                          購外幣困難<lb/>
                   </div>
                   <div>
                          <p>
                               （東京廿六日路<lb/>
                               透電）旅客自日本<lb/>
                               赴上海、天津、及<lb/>
                               日圓打折扣行用之<lb/>
                               各地者、今後苟非<lb/>
                               得大藏省特准、不<lb/>
                               復能有日本各銀行<lb/>
                               購買外幣、欲購此<lb/>
                               以備途中使用者、<lb/>
                               須出其護照、由售<lb/>
                               出外幣之銀行蓋章<lb/>
                               、並載明日期與所<lb/>
                               兌日圓之數額、大<lb/>
                               藏省已以此兩項規<lb/>
                               則、通吿日本各銀<lb/>
                               行、而於四月十五<lb/>
                               日實行矣、<lb/>
                          </p>
                   </div>
            </div>
            <div type="article">
                   <div>
                          德土締結<lb/>
                          通航協定<lb/>
                   </div>
                   <div>
                          <p>
                               （土耳其京城廿<lb/>
                               六日海通電）關於<lb/>
                               開航柏林與斯丹埠<lb/>
                               間商業航空線之協<lb/>
                               定已於昨日在此間<lb/>
                               經土耳其交通部長<lb/>
                               賽蒂加耶、與德國<lb/>
                               盧夫漢薩航空公司<lb/>
                               代表温特斐德、正<lb/>
                               式簽字、開新航線<lb/>
                               通航日期、訂於六<lb/>
                               月一日云、<lb/>
                          </p>
		       </div>
            </div>
            <div type="article">
                   <div>
                          德國社黨表示<lb/>
                          不受英國軟化<lb/>
                          準備留難英使漢德森<lb/>
                   </div>
                   <div>
                          <p>
                               （柏林廿六日美<lb/>
                               聯電）國社黨方面<lb/>
                               昨晚表示、希特勒<lb/>
                               於四月廿八日、向<lb/>
                               國會發表演說時、<lb/>
                               或將不顧英國軟化<lb/>
                               德方、對美答覆之<lb/>
                               企圖、同時德政府<lb/>
                               、似已準備對英國<lb/>
                               駐柏林大使漢德森<lb/>
                               、予以留難、漢氏<lb/>
                               始於昨日囘返柏林<lb/>
                               、並帶有致希特勒<lb/>
                               之警告牒文一件、<lb/>
                          </p>
                          <p>
                               （柏林廿六日路<lb/>
                               透電）英國駐德大<lb/>
                               使漢特森、與希特<lb/>
                               勒昨日之晤談、並<lb/>
                               未實現、<lb/>
                          </p>
                   </div>
            </div>
            <div type="article">
                   <div>
                          義爲蘇造艦<lb/>
                   </div>
                   <div>
                          <p>
                               （羅馬廿六日海<lb/>
                               通電）義大利爲蘇<lb/>
                               聯所建造之大驅逐<lb/>
                               艦、「達係坎特」<lb/>
                               號、自完工以後、<lb/>
                               迭次試航、已證明<lb/>
                               爲世界最速之戰艦<lb/>
                               、昨日自里洪起椗<lb/>
                               、駛往奧德莎、然<lb/>
                               後繼續駛往斯丹埠<lb/>
                               、交予蘇聯當局接<lb/>
                               收、艦中之所有義<lb/>
                               籍水手、換乘「奧<lb/>
                               蘭多」號汽艇返國<lb/>
                               、該艦速率爲四十<lb/>
                               二浬、裝有十三生<lb/>
                               的口徑之大炮六尊<lb/>
                               、高射炮六尊、及<lb/>
                               魚雷發射管九支云<lb/>
                          </p>
                   </div>
            </div>
            <div type="article">
                   <div>
                          英輪被扣留<lb/>
                          向日提抗議<lb/>
                   </div>
                   <div>
                          <p>
                               （香港廿六日路<lb/>
                               透電）四月八日被<lb/>
                               日海軍扣留之英輪<lb/>
                               西格利斯號輪員與<lb/>
                               水夫、昨日午後自<lb/>
                               貝斯加杜萊斯島、<lb/>
                               乘廣州丸返抵此間<lb/>
                               、該輪則被扣留以<lb/>
                               待續加查究、輪中<lb/>
                               所載食鹽八十噸、<lb/>
                               已被沒收、則英當<lb/>
                               局已向日海軍當局<lb/>
                               提出强硬抗議、此<lb/>
                               案現已提交日外務<lb/>
                               省、<lb/>
                          </p>
                   </div>
            </div>
            <div type="article">
                   <div>
                          長篇<lb/>
                          小說<lb/>
                   </div>
                   <div>
                          新上海春秋<lb/>
                   </div>
                   <div>
                          （三四一）<lb/>
                   </div>
                   <div>
                          天笑<lb/>
                   </div>
                   <div>
                          第十八囘　姿宴游餐館小排當　窮奢欲博塌新巡禮<lb/>
                   </div>
                   <div>
                          <p>
                               且說周局長送楊賓秋到了柳老五那裏，自行囘去，約定明日再行會見，晚上<lb/>
                               可以同吃小館子。柳老五也約定楊賓秋明日下午再來，略略耽擱，已經到時候<lb/>
                               了。便打了個電話給祥生汽車行，雇了車子，囘到家裏。家中人很相信，以爲<lb/>
                               老爺是由南京剛到家裏。唐太太不是預先關照了徐媽，倘然你們老爺囘來了，<lb/>
                               立刻打個電話來，我們可以送你們太太囘家。現在楊賓秋歸家，見他夫人不在<lb/>
                               家裏，心知是囘娘家去了。徐媽以爲賓秋不知唐少魯被綁的事，還絮絮叨叨的<lb/>
                               告訴他，說是：『唐老太爺被綁的那天晚上，夜裏有九點鐘了，老太太用汽車<lb/>
                               來接了太太去了，連小小姐也帶了去了，阿寶也去了。那邊老太太關照，老爺<lb/>
                               囘來後，打電話去通知，她那裏用汽車送太太囘來。我就打電話去！』賓秋道<lb/>
                               ：『辰光不太遲了嗎？或者太太已經睡了，也未可知。』徐媽道：『今天是禮<lb/>
                               拜六，太太盼望老爺囘來，一定是沒有睡的。况且他們關照我打電話去的，我<lb/>
                               總得打電話去。』賓秋被徐媽這樣一說，自己也覺得有些內愧，　想她們還以<lb/>
                               爲我忙裏偷閑，到星期六方纔囘家，豈知我在星期四的晚上，已經到了上海，<lb/>
                               只是躱在別處罷了。<lb/>
                          </p>
                   </div>				
            </div>
            <div type="advert" dir="rtl" mode="horizontal-tb">
                   <div>
                          胃鑰<lb/>
                   </div>
                   <div dir="rtl" mode="vertical-rl">
                          分片<lb/>
                          &gaiji;&gaiji;<lb/>
                   </div>
                   <div>
                          增進消化能力<lb/>
                          主治肝胃氣痛<lb/>
                          抑止吞酸嘔吐<lb/>
                   </div>
                   <div type="image"></div>
                   <div type="image"></div>
                   <div type="image"></div>
                   <div>
                          上海中西大藥房發行<lb/>
                   </div>
            </div>
            <div type="advert">
                   <div dir="rtl" mode="horizontal-tb">		
                          金字塔香煙<lb/>
                   </div>	
                   <div type="image"></div>
                   <div>
                          煙中<lb/>
                   </div>
                   <div>
                          鐵軍<lb/>
                   </div>
                   <div dir="rtl" mode="horizontal-tb"> 					
                          中國福新煙公司出品<lb/>
                   </div>			
             </div>
             <div type="margin">
                    廣告刊例：　報名旁　每日每方二十元　長行計七寸高　每日每行一元八角　短行計三寸半高　每日每行九角　中縫計三寸半高二寸濶　每日每格八元<pb/>
             </div>
      </div>
	<!--start middle of the fold-->
      <div dir="rtl" mode="vertical-rl">
             <div type="advert">
                    <div>
                           董惠民醫師<lb/>
                    </div>
                    <div dir="rtl" mode="horizontal-tb">
                           （地址）<lb/>
                    </div>
                    <div>
                            四馬路天蟾舞<lb/>
                            台斜對面大西<lb/>
                            洋菜社西首第<lb/>
                            二家崇善醫院<lb/>
                    </div>
                    <div dir="rtl" mode="horizontal-tb">
                            時間<lb/>
                    </div>
                    <div>
                            上午九時起<lb/>
                            下午九時止<lb/>
                            星期照常●<lb/>
                    </div>
                    <div>
                            淋病最易傳染而最難斷根　欲求澈底斷根　首宜用最高倍顯微鏡驗檢毒菌種類爲（單純性）（<lb/>
                            混合性）（抑無淋毒性）分門別類　施以有效療法　對於慢性淋病　更須用尿道反光鏡檢查尿<lb/>
                            道　視淋菌破壞程度及潛伏深淺　參以特殊療法　故白濁並非眞正不能斷根　惟須賴●學識●<lb/>
                            手術●經驗●設備俱優之醫師　始克奏功　若不明淋菌種類　槪以同一方法治療　有經數月電<lb/>
                            療注射患者仍未全愈　治淋者不明自己療法錯誤　反斥患者不善攝養　而自詡用藥眞確　療械<lb/>
                            新穎　臨診悠久　寗非可憾　本醫師對於淋病及花柳各科　雖不敢自詡獨步　然必竭盡貢獻<lb/>
                            務使患者不受－時間－經濟－精神等痛苦　而獲澈底斷根　廿餘年來幸能百不失一尚覺差可自慰<lb/>
                            茲爲節省病家<lb/>
                            經濟起見初期<lb/>
                    </div>
                    <div>
                            白濁　梅毒　橫痃下疳<lb/>
                    </div>
                    <div>
                            槪收<lb/>
                            藥本<lb/>
                    </div>
                    <div>
                            拾圓<lb/>
                    </div>
                    <div>
                            打針服藥電療　永不復發<lb/>
                            驗檢完全在內　生育照常<lb/>
                    </div>
                    <div>
                            特備長短波電療機　最高倍顯微鏡　橫痃消散機　尿道檢查鏡　義務助治愈後可向衞生局檢驗斷根<lb/>
                    </div>
             </div>
             <div type="advert">
                    <div>
                           上海河南<lb/>
                           路四馬路<lb/>
                           口第一家<lb/>
                    </div>
                    <div>
                           冼種福堂<lb/>
                    </div>
                    <div>
                           電話　九五四一〇<lb/>
                           諧音　叫吾試益靈<lb/>
                    </div>
                    <div>
                           逢<lb/>
                           止咳藥<lb/>
                           靈<lb/>
                    </div>
                    <div>
                           救母<lb/>
                           經驗<lb/>
                    </div>
                    <div>
                           救母止咳散<lb/>
                    </div>
                    <div>
                           風寒咳嗽氣喘<lb/>
                           痰壅當晚見效<lb/>
                    </div>
                    <div>
                           超人<lb/>
                           一等<lb/>
                    </div>
                    <div>
                           馬寶猴棗散<lb/>
                    </div>
                    <div>
                           小兒除痰止咳<lb/>
                           退熱第一良藥<lb/>
                    </div>
                    <div>
                           痰喘<lb/>
                           必靈<lb/>
                    </div>
                    <div>
                           龍涎哮喘丸<lb/>
                    </div>
                    <div>
                           耑治哮喘氣急<lb/>
                           日久咳嗽必愈<lb/>
                    </div>
                    <div>
                           寒熱往來　咳嗽痰喘　偶患斯疾　宜早治之<lb/>
                           本堂咳藥　確有經驗　請嘗試之　方知不謬<lb/>
                    </div>
             </div>
             <div type="advert">
                    <div>
                           東　南　醫　院<lb/>
                    </div>
                    <div>
                           施診　每日上午八時至十時　　號金貳角四分<lb/>
                           例診　每日上午十時至十二時　診金陸角<lb/>
                           特診每日下午一時至五時　　　診金壹元叁角<lb/>
                           出診　　隨　請　隨　診　　　診金七元<lb/>
                           卽日起施種牛痘祗收號金不另取費<lb/>
                           本院設有病室環境幽靜空氣淸新適於療養<lb/>
                           院址法租界薩坡賽路二九九號電話八〇六〇八號<lb/>
                    </div>
             </div>
      </div>
      <!-- start recto page -->
      <div type="page" page="recto" n="3" dir="rtl" mode="vertical-rl">
             <div type="margin" dir="rtl" mode="horizontal-tb">
                    中華民國二十八年四月廿七日　晶報　星期四　第三版<lb/>
             </div>
             <div type="article">
                    <div>
                           工部局三樓發生<lb/>
                           日籍巡捕自殺案<lb/>
                           發覺尚早切腹未遂<lb/>
                    </div>
                    <div>
                           <p>
                                工部局自允日方之請求、添用日籍巡捕後、卽進行添用、<lb/>
                                最近由日僱到大批日捕到滬、但彼輩抵滬後、因不諳上海情<lb/>
                                形、以及一切交通章程等、故須加以練習、然後再行分配職<lb/>
                                務、日捕中有名井上其人、在日賦閑已久、潦倒無狀、滿意<lb/>
                                一到中國、卽可派到職司、不圖來華後、大失所望、於是抑<lb/>
                                鬱異常、竟在昨日下午三時餘、在工部局三樓圖盡、實行切<lb/>
                                腹、所幸發覺尚早、傷勢不重、若此人者、可見其窮極志短<lb/>
                                之一般也、<lb/>
                           </p>
                    </div>
             </div>			
             <div type="article">
                    <div>
				六年前一舊案<lb/>
				槍殺高阿根未遂犯<lb/>
				最高法院發回重審<lb/>
                    </div>
                    <div>
                           <p>
                                向以販賣紅丸毒品常業之童田華、<lb/>
                                李金山、沈榮生等、因與同黨高阿根等<lb/>
                                、爭奪權利關係、以致結仇、於民國廿<lb/>
                                二年八月六日上午三時、結夥在福州路<lb/>
                                會樂里口、用手槍轟擊高阿根、結果未<lb/>
                                遂、至同月廿九日上午、童李二人、在九<lb/>
                                江路被捕拘獲、解院訊判、童處刑十五<lb/>
                                年、李十二年、已三審確定、送監執行<lb/>
                                、其同謀犯沈榮生、去年六月九日、亦<lb/>
                                被拘、訊判徒刑五年、上訴高二分院遭<lb/>
                                駁囘後、又上訴最高法院、茲由最高法<lb/>
                                院發囘重審、昨晨開庭、<lb/>
                           </p>
                    </div>
                    <div>
                           據沈供稱<lb/>
                    </div>
                    <div>
                           <p>
                                我與<lb/>
                                高阿<lb/>
                                根向不認識、亦素<lb/>
                                無仇怨、我何必要<lb/>
                                打死他、又據李供<lb/>
                                稱、我被判吃十二<lb/>
                                年官司實寃枉、不<lb/>
                                過高阿根一定說有<lb/>
                                我、我亦無法子、<lb/>
                                現在我已判决確定<lb/>
                                、本不願再講過去<lb/>
                                事情、我與沈素不<lb/>
                                認識、怎能與他一<lb/>
                                起去殺人呢？我們<lb/>
                                已被高阿根害得很<lb/>
                                苦了、希望他不要<lb/>
                                再害別人、高阿根<lb/>
                                究係何等人物、大<lb/>
                                槪住在上海的人都<lb/>
                                知道、他現在又在<lb/>
                                滬西開賭窟、末據<lb/>
                                承辦探員向庭上報<lb/>
                                吿稱、我到高阿根<lb/>
                                住所去傳他時、他<lb/>
                                家裏人說不在上海<lb/>
                                、到香港去了、平<lb/>
                                日來往港滬無定、<lb/>
                                庭諭上訴人還押、<lb/>
                                候改期再訊、<lb/>
                           </p>
                    </div>
             </div>
             <div type="article">
                    <div>
                           孀婦家<lb/>
                           匪徒覬覦行劫<lb/>
                           損失六千餘元<lb/>
                    </div>
                    <div>
                           <p>
                                孀婦王婉貞、寓<lb/>
                                居法租界勞爾東路<lb/>
                                靑雲坊廿二號、家<lb/>
                                境尚裕、致啓匪徒<lb/>
                                覬覦、前日（廿五<lb/>
                                日）中午十二時許<lb/>
                                、王正在家午聚時<lb/>
                                、突有年約廿餘歲<lb/>
                                之盜匪四名闖入、<lb/>
                                搶刦歷一小時之久<lb/>
                                、計搶去首飾衣服<lb/>
                                現鈔、値洋六千餘<lb/>
                                元之鉅、<lb/>
                           </p>
                    </div>
             </div>
             <div type="article">
                    <div dir="rtl" mode="horizontal-tb">
                           老正和改組<lb/>
                           經理被控<lb/>
                    </div>
                    <div>
                           <p>
                                老正<lb/>
                                和染坊<lb/>
                                經理王<lb/>
                                月樓、<lb/>
                                及職員<lb/>
                                魯志獻<lb/>
                                、近被<lb/>
                                該坊股東吳泉生、<lb/>
                                控吿串通侵占背信<lb/>
                                等罪、該案昨日午<lb/>
                                後三時傳訊、吳泉<lb/>
                                生供述被吿、王月<lb/>
                                樓等、未得自訴人<lb/>
                                之同意、擅將老正<lb/>
                                和染坊改組、自訴<lb/>
                                人登報反對、被告<lb/>
                                置<!-- character shows font-dependent variations, char found here: ⿱四⿺𠃊𥃭 -->之不理、繼由魯<lb/>
                                王相繼供稱、吳泉<lb/>
                                生虛構事實、諭令<lb/>
                                辯論一過、定五月<lb/>
                                二日宣判、<lb/>
                           </p>
                    </div>
             </div>
             <div type="article">
                    <div>
                           僞『局員』活動<lb/>
                           搜查五角場<lb/>
                           耿壽寶暗殺案揭曉<lb/>
                    </div>
                    <div>
                           <p>
                                前夜七時起、至昨晨四時半止、僞『<lb/>
                                上海市警察局偵緝隊』、在滬西曹家渡<lb/>
                                五角場一帶、大事搜捕、當在該處一三<lb/>
                                一四號前樓、捕去周子英、並抄出盒子<lb/>
                                鎗一枝、手槍一枝、押往僞『局』、據<lb/>
                                供彼等徒黨、共有二十二人、首領名謝<lb/>
                                祥林、前次槍殺僞偵緝隊長耽壽寶、卽<lb/>
                                係渠等所爲云、現僞局據詞後、已大事<lb/>
                                活動、昨日該處一帶、仍在查勘中云、<lb/>
                           </p>
                    </div>
             </div>
		<div type="article">
                   <div>
                          外│交│界<lb/>
                   </div>
                   <div>
                          <p>
                               廿六日法文上海<lb/>
                               日報載、法國駐華<lb/>
                               大使署秘書蒲法奈<lb/>
                               、自中日戰事起後<lb/>
                               、曾奉調至天津法<lb/>
                               領事署服務、茲聞<lb/>
                               已於昨日抵滬、轉<lb/>
                               程返法休假、<lb/>
                          </p>
                          <p>  
                               （又訊）比利時<lb/>
                               駐華大使紀佑穆男<lb/>
                               爵夫婦、昨已趁船<lb/>
                               返國、<lb/>
                          </p>
                   </div>
             </div>
             <div type="article">
                    <div dir="rtl" mode="horizontal-tb">
                           日倉庫大火<lb/>
                    </div>
                    <div>
                           日警探出動密查<lb/>
                           捕獲縱火人<lb/>
                           並獲嫌疑犯八人<lb/>
                    </div>
                    <div>
                           <p>
                                虹口黃浦路日郵船會社第二倉<lb/>
                                庫、於上月廿四日、發生大火、<lb/>
                                當時直延及日領館<lb/>
                                警察署、損失達五<lb/>
                                十萬以上、事後日<lb/>
                                方警探、紛紛出動<lb/>
                                密查、謂該次起火<lb/>
                                、實由華方之放火<lb/>
                                團體所爲、迄至昨<lb/>
                                日、日方始宣佈、<lb/>
                                據稱於事後曾捕獲<lb/>
                                該團領袖靑年華人<lb/>
                                陳康泰一名、及嫌<lb/>
                                疑者八人、並謂陳<lb/>
                                已供認參加該次之<lb/>
                                放火行爲、至嫌疑<lb/>
                                者、則尚在密訊中<lb/>
                                云、<lb/>
                           </p>
                    </div>
             </div>
             <div type="article">
                    <div>
                           暗殺楊再三未遂案<lb/>
                           雙方供詞各執<lb/>
                           改期五月一日再訊<lb/>
                    </div>
                    <div>
                           <p>
                                本月六日中午十<lb/>
                                二時許、東新橋口<lb/>
                                、有一常熟人楊再<lb/>
                                三、被人開槍暗殺<lb/>
                                未遂、事後、經捕<lb/>
                                獲開槍之徐子懋一<lb/>
                                名、供出由熊桂松<lb/>
                                主使、以三百代價<lb/>
                                、囑其殺楊、該案<lb/>
                                昨又審訊、被害人<lb/>
                                楊再三到庭陳述、<lb/>
                                有樊發林者、本任<lb/>
                                合興輪職員、欠其<lb/>
                                借欵二千五百元、<lb/>
                                曾向其催索、致老<lb/>
                                羞成怒、串同熊桂<lb/>
                                松、使人將其暗殺<lb/>
                                等語、詰之被告、<lb/>
                                供稱熊司令按卽熊<lb/>
                                桂松與其有仇、故<lb/>
                                由周國光介紹其殺<lb/>
                                楊、庭上核詞、以<lb/>
                                尚須調查、諭改期<lb/>
                                五月一日再訊云、<lb/>
                           </p>
                    </div>
             </div>
             <div type="article">
                    <div dir="rtl" mode="horizontal-tb">
                           大批土犯被捕<lb/>
                           抄出巨量煙土<lb/>
                    </div>
                    <div>
                           <p>
                                工部局禁毒科、<lb/>
                                昨在福建路永安旅<lb/>
                                社卅二號房間、拘<lb/>
                                獲煙土販王春三、<lb/>
                                等數名<lb/>
                                、抄出<lb/>
                                煙土二<lb/>
                                百兩、<lb/>
                                根據王<lb/>
                                之供詞<lb/>
                                、續獲<lb/>
                                男女犯<lb/>
                                共十三名、抄出烟<lb/>
                                土八百二十兩、昨<lb/>
                                晨解院、諭還押改<lb/>
                                期七天再訊、<lb/>
                           </p>
                    </div>
             </div>
             <div type="article">
                    <div>
                           冠華里<lb/>
                           捕去一毒販韓人<lb/>
                    </div>
                    <div>
                           <p>
                                昨日上午十一時<lb/>
                                左右、法租界辣斐<lb/>
                                德路冠華里三號、<lb/>
                                突遭日方所派人員<lb/>
                                、會同法捕房中西<lb/>
                                探員、搜查結果、<lb/>
                                捕去販毒犯韓人男<lb/>
                                子一名云、<lb/>
                           </p>
                    </div>
             </div>
             <div type="article">
                    <div>
                           死狗死貓<lb/>
                           其肉豈可供食<lb/>
                    </div>
                    <div>
                           賣肉者處刑<lb/>
                    </div>
                    <div>
                           <p>
                                小販鍾興林、以<lb/>
                                販賣野味熟品爲業<lb/>
                                、近有人致函衞生<lb/>
                                處、報吿鍾所出售<lb/>
                                之燒熟兔肉、均係<lb/>
                                死狗死貓之肉所冒<lb/>
                                充、日前新閘捕房<lb/>
                                派探在康腦脫路八<lb/>
                                十七弄、將鍾拘獲、<lb/>
                                據供此項肉食、係<lb/>
                                向謝阿寶購買、遂<lb/>
                                又將謝逮捕、昨解<lb/>
                                特一院、各處徒刑<lb/>
                                三月、<lb/>
                           </p>
                    </div>
             </div>
             <div type="article">
                    <div>
                           招頂房屋施行騙術<lb/>
                           中外圖書公司主被控<lb/>
                    </div>
                    <div>
                           <p>
                                現住靜安大樓三<lb/>
                                三六號中外圖書公<lb/>
                                司主人盛際唐等、<lb/>
                                近被亞利酒家職員<lb/>
                                王德心、控吿詐欺<lb/>
                                、緣被告等於本年<lb/>
                                三月十五日、登報<lb/>
                                招頂謂有坐落亞爾<lb/>
                                培路梅谷公寓三七<lb/>
                                六號有大店面一間<lb/>
                                、原係開設書店、<lb/>
                                刻因主人另有別圖<lb/>
                                、願廉價出頂、當<lb/>
                                時自訴人前往接洽<lb/>
                                、議定頂價一千六<lb/>
                                百七十元、先付定<lb/>
                                洋一百元、餘欵約<lb/>
                                於三月二十日付給<lb/>
                                五百七十元、及支<lb/>
                                票三百三十元、六<lb/>
                                百元二紙、詎知至<lb/>
                                三月三十一日連同<lb/>
                                各種契約交出、始<lb/>
                                知該屋在四月一日<lb/>
                                業已期滿、同時業<lb/>
                                主亦已函知盛際唐<lb/>
                                遷讓、至此始知受<lb/>
                                騙、昨日傳審、&gaiji;問<lb/>
                                雙方一過、諭改期<lb/>
                                五月一日再審云、<lb/>
                           </p>
                    </div>
             </div>
             <div type="article">
                    <div>
                           防衞上海<lb/>
                    </div>
                    <div>
                           法後備軍<lb/>
                           今晚練習<lb/>
                    </div>
                    <div>
                           <p>
                                本市法僑後備役<lb/>
                                各下級軍官、定今<lb/>
                                晚六時、在福履理<lb/>
                                路法國兵營內、舉<lb/>
                                行「防衞上海之訓<lb/>
                                練」、其課程爲砲<lb/>
                                隊及工程隊之運用<lb/>
                           </p>
                    </div>
             </div>
             <div type="article">
                    <div>
                           ◇小消息◇<lb/>
                    </div>
                    <div>
                           <p>
                                ▲前市立新民小<lb/>
                                學教員、共同籌組<lb/>
                                上海模範小學、全<lb/>
                                部共分八學級、推<lb/>
                                潘鼎元爲校長、<lb/>
                           </p>
                           <p>
                                ▲去年一年間、<lb/>
                                漏貼印花&gaiji;而處罰<lb/>
                                者、百零七件、此<lb/>
                                係根據捕房律師之<lb/>
                                報吿、<lb/>
                           </p>
                           <p>
                                ▲小呂宋華東國<lb/>
                                貨商場主人蔡聯發<lb/>
                                、節省宴費、計國<lb/>
                                幣二百元、昨已悉<lb/>
                                數送交廣東路難民<lb/>
                                救濟協會、<lb/>
                           </p>
                           <p>
                                ▲遊藝界領袖劉<lb/>
                                子雲、今日爲其生<lb/>
                                母嗣母兩太　人七<lb/>
                                秩賀壽、假座寧波<lb/>
                                同鄉會公祝、所有<lb/>
                                公份壽儀、悉移助<lb/>
                                救難經費、<lb/>
                           </p>
                           <p>
                                ▲江淮中學每週<lb/>
                                、聘請名士講學、<lb/>
                                本星期二特請大海<lb/>
                                中學校長聶海帆演<lb/>
                                「學生之品德與社<lb/>
                                會之關係」、<lb/>
                           </p>
                    </div>
             </div>
             <div type="article">
                    <div>
                           少。女。怨<lb/>
                           父母擇婚不愼之害<lb/>
                    </div>
                    <div>
                           <p>
                                本市錢業巨子孫劼卿、擁<lb/>
                                資數百萬、妻徐氏、妾老五<lb/>
                                、同居一處、徐氏曾生一女<lb/>
                                名<lb/>
                           </p>
                     </div>
                     <div>
                            永和<lb/>
                     </div>
                     <div>
                            <p>
                                 現年二十有二、素<lb/>
                                 爲父母所鍾愛、但<lb/>
                                 自老五爲孫簉室後、不但孫<lb/>
                                 爲所蠱惑、徐氏亦聽信讒言<lb/>
                                 、待遇親女、從此易愛爲憎<lb/>
                                 、復經老五慫恿、將永和嫁<lb/>
                                 與沈比德爲婦、結婚之後、<lb/>
                                 始發覺沈在廣西原籍、早有<lb/>
                                 妻室、當時<lb/>
                            </p>
                     </div>
                     <div>
                            永和<lb/>
                     </div>
                     <div>
                            <p>
                                 年僅二九、雖怨父<lb/>
                                 母擇耦不愼、然而<lb/>
                                 木已成舟、徒恨無裨、勉相<lb/>
                                 共處、數年間、計育四子、<lb/>
                                 前歲初夏、沈擕第三子囘籍<lb/>
                                 、去後被永和查出所有奩中<lb/>
                                 飾物、大部爲沈取殆盡、故<lb/>
                                 是年歲尾、沈獨自由桂歸來<lb/>
                            </p>
                     </div>
                     <div>  
                            永和<lb/>
                     </div>
                     <div>
                            <p>
                                 旣痛愛子不返、更<lb/>
                                 忿良人無恥、益咎<lb/>
                                 其父母始謀不善、害伊終身<lb/>
                                 、歸與雙親交涉、並責老五<lb/>
                                 之爲禍首罪魁、時孫及其妻<lb/>
                                 妾、亦自悔孟浪、遂圖補救<lb/>
                                 、命女投新閘捕房、告發沈<lb/>
                                 重婚、當經捕房對周提起公<lb/>
                                 訴後、以被吿傳不到案、至<lb/>
                                 上年五月十日、由法院出函<lb/>
                                 拘提、乃沈自知罪有應得、<lb/>
                                 乘機潛逃、故該案迄猶虛懸<lb/>
                                 、而孫<lb/>
                            </p>
                     </div>
                     <div>
                            永和<lb/>
                     </div>
                     <div>
                            <p>
                                 爾後遂囘母家、依<lb/>
                                 父度日、詎居未久<lb/>
                                 、復因父妾及老五、乘間挑<lb/>
                                 撥、致父女間惡感愈深、馴<lb/>
                                 至由永和延律師對其親生父<lb/>
                                 母及老五、提起返還存欵數<lb/>
                                 萬金、與給付伊終身生活費<lb/>
                                 之訴訟、此案發生踰今甫數<lb/>
                                 月、現該孫<lb/>
                            </p>
                     </div>
                     <div>
                            永和<lb/>
                     </div>
                     <div>
                            <p>
                                 、又延律師對沈比<lb/>
                                 德提起撤銷婚姻之<lb/>
                                 訴、並以被吿蹤跡不明、請<lb/>
                                 求公示送達、昨日庭審理、<lb/>
                                 原吿患病未到、庭上以尚須<lb/>
                                 調查證據、諭今改期再訊，<lb/>
                            </p>
                     </div>
             </div>
             <div type="advert">
                    <div>
                           質<lb/>
                    </div>
                    <div>
                           香<lb/>
                    </div>
                    <div>
                           味<lb/>
                    </div>
                    <div>
                           效<lb/>
                    </div>
                    <div type="image"></div>
                    <div dir="ltr" mode="horizontal-tb">
                           BIOZYGEN<lb/>
                    </div>
                    <div>
                           上海新亞藥廠製造<lb/>
                    </div>
                    <div>
                           藥房均售<lb/>
                    </div>
                    <div>
                           寶青春<lb/>
                    </div>
                    <div dir="ltr" mode="horizontal-tb">
				&gaiji;&gaiji;&gaiji;3L<lb/>
                    </div>
                    <div>
                           寶青春爲眞正麥酒乾燥酵母精製。富含各<lb/>
                           種惟他命。功能開胃强身。治療脚氣。整<lb/>
                           理胃腸。促進新陳代謝。產生新活力。質<lb/>
                           香味效。無不超人一等。<lb/>
                    </div>
                    <div dir="rtl" mode="horizontal-tb">
                           質香味效<lb/>
                    </div>
                    <div>
                           含量充足<lb/>
                           芬芳開胃<lb/>
                           鮮美可口<lb/>
                           靈騐偉大<lb/>
                    </div>
                    <div type="image"></div>
             </div>		
             <div type="article">
                    <div>
                           今雜事祕<lb/>
                    </div>
                    <div>
                           △井波<lb/>
                    </div>
                    <div dir="rtl" mode="horizontal-tb">
                           （五）<lb/>
                    </div>
                    <div>
                           提刀人譔<lb/>
                    </div>
                    <div>
                           <p>
                                冠玉笑曰：「新衣之來，須四小時也，四小時須二百四十分也，設不惡作<lb/>
                                劇，將何以遣此長時間哉！」明珠沉思有頃，嫣然曰：「汝不嘗爲我誦詩經<lb/>
                                乎？詩經之第一章曰：規規矩矩，在河之洲，窈窕淑女，君子好逑。汝倘能<lb/>
                                規規矩矩，則我無不從命。」冠玉曰：「可」，卽解衣；旣而曰：「登」，<lb/>
                                卽登牀；旣而曰：「起」，卽起與明珠爲禮。此所謂禮，在冠玉亦不自知爲<lb/>
                                周公之禮耶，抑爲待罪行間之舉槍禮耶。明珠以言猶在耳，視爲不可卻，第<lb/>
                                小語曰：「頃汝言將於父母前，謂已與我好合，言時不知今之能不幸而言中<lb/>
                                也。」冠玉曰：「是以知我將於父母前，謂汝已有業，亦必不幸而言中也」<lb/>
                                。明珠又欲窺視其腹，心則惴惴然，念：「頃我窺視，樂而肇禍，今茲幸毋<lb/>
                                肇禍。」然明珠一舉首，不謂禍猶方興未艾，蓋逆旅中設錦衾角枕，以誘顧<lb/>
                                客之睡眠，今以睡眠之故，乃致衾褥於斑斑點點，如落紅之一陣，呼曰：「<lb/>
                                孼哉！」冠玉曰：「此固無足異，凡斑斑點點之處，我以花花綠綠掩之，大<lb/>
                                事化小事，小事化無事矣。」明珠知花花綠綠者，鈔幣也。<lb/>
                           </p>
                    </div>
             </div>
             <div type="margin" dir="rtl" mode="vertical-rl">
                    定報價目：　本埠　每月五角　三個月一元四角　外埠　每月六角　三月一元七角　半年三元二角　全年六元　郵費在內　國外加倍報資先惠<pb/>
             </div>
      </div>
</fold>